Workbook

Sheet RAW_DATA
A1: Authors | B1: Title | C1: Year | D1: Source title | E1: Volume | F1: Issue | G1: Art. No. | H1: Page start | I1: Page end | J1: Cited by | K1: DOI | L1: Link | M1: Document Type | N1: Publication Stage | O1: Open Access | P1: Source | Q1: EID | R1: [Autofills] NOT IN PAPERS | S1: [Autofills] Is Duplicate?
A2: Stepin I.; Alonso J.M.; Catala A.; Pereira-Farina M. | B2: A Survey of Contrastive and Counterfactual Explanation Generation Methods for Explainable Artificial Intelligence | C2: 2021 | D2: IEEE Access | E2: 9 | G2: 9321372 | H2: 11974 | I2: 12001 | J2: 340 | K2: 10.1109/ACCESS.2021.3051315 | L2: https://www.scopus.com/pages/publications/85099601493?origin=resultslist | M2: Review | N2: Final | O2: All Open Access; Gold Open Access; Green Open Access | P2: Scopus | Q2: 2-s2.0-85099601493 | R2: =COUNTIF( Papers!G:G, RAW_DATA!Q2 ) = 0 -> FALSE | S2: =(COUNTIF(B:B, B2) > 1 ) -> FALSE
A3: Nazar M.; Alam M.M.; Yafi E.; Su'Ud M.M. | B3: A Systematic Review of Human-Computer Interaction and Explainable Artificial Intelligence in Healthcare with Artificial Intelligence Techniques | C3: 2021 | D3: IEEE Access | E3: 9 | H3: 153316 | I3: 153348 | J3: 263 | K3: 10.1109/ACCESS.2021.3127881 | L3: https://www.scopus.com/pages/publications/85119430656?origin=resultslist | M3: Review | N3: Final | O3: All Open Access; Gold Open Access; Green Open Access | P3: Scopus | Q3: 2-s2.0-85119430656 | R3: =COUNTIF( Papers!G:G, RAW_DATA!Q3 ) = 0 -> FALSE | S3: =(COUNTIF(B:B, B3) > 1 ) -> FALSE
A4: Young A.T.; Amara D.; Bhattacharya A.; Wei M.L. | B4: Patient and general public attitudes towards clinical artificial intelligence: a mixed methods systematic review | C4: 2021 | D4: The Lancet Digital Health | E4: 3 | F4: 9 | H4: e599 | I4: e611 | J4: 264 | K4: 10.1016/S2589-7500(21)00132-1 | L4: https://www.scopus.com/pages/publications/85115041953?origin=resultslist | M4: Review | N4: Final | O4: All Open Access; Gold Open Access | P4: Scopus | Q4: 2-s2.0-85115041953 | R4: =COUNTIF( Papers!G:G, RAW_DATA!Q4 ) = 0 -> FALSE | S4: =(COUNTIF(B:B, B4) > 1 ) -> FALSE
A5: Rashid A.B.; Kausik M.A.K. | B5: AI revolutionizing industries worldwide: A comprehensive overview of its diverse applications | C5: 2024 | D5: Hybrid Advances | E5: 7 | G5: 100277 | J5: 486 | K5: 10.1016/j.hybadv.2024.100277 | L5: https://www.scopus.com/pages/publications/85204730281?origin=resultslist | M5: Review | N5: Final | O5: All Open Access; Gold Open Access; Green Open Access | P5: Scopus | Q5: 2-s2.0-85204730281 | R5: =COUNTIF( Papers!G:G, RAW_DATA!Q5 ) = 0 -> FALSE | S5: =(COUNTIF(B:B, B5) > 1 ) -> FALSE
A6: Tong S.; Jia N.; Luo X.; Fang Z. | B6: The Janus face of artificial intelligence feedback: Deployment versus disclosure effects on employee performance | C6: 2021 | D6: Strategic Management Journal | E6: 42 | F6: 9 | H6: 1600 | I6: 1631 | J6: 371 | K6: 10.1002/smj.3322 | L6: https://www.scopus.com/pages/publications/85109705359?origin=resultslist | M6: Article | N6: Final | O6: All Open Access; Hybrid Gold Open Access | P6: Scopus | Q6: 2-s2.0-85109705359 | R6: =COUNTIF( Papers!G:G, RAW_DATA!Q6 ) = 0 -> FALSE | S6: =(COUNTIF(B:B, B6) > 1 ) -> FALSE
A7: Zhang T.; Tao D.; Qu X.; Zhang X.; Zeng J.; Zhu H.; Zhu H. | B7: Automated vehicle acceptance in China: Social influence and initial trust are key determinants | C7: 2020 | D7: Transportation Research Part C: Emerging Technologies | E7: 112 | H7: 220 | I7: 233 | J7: 398 | K7: 10.1016/j.trc.2020.01.027 | L7: https://www.scopus.com/pages/publications/85078934939?origin=resultslist | M7: Article | N7: Final | P7: Scopus | Q7: 2-s2.0-85078934939 | R7: =COUNTIF( Papers!G:G, RAW_DATA!Q7 ) = 0 -> FALSE | S7: =(COUNTIF(B:B, B7) > 1 ) -> FALSE
A8: Tussyadiah I.P.; Zach F.J.; Wang J. | B8: Do travelers trust intelligent service robots? | C8: 2020 | D8: Annals of Tourism Research | E8: 81 | G8: 102886 | J8: 280 | K8: 10.1016/j.annals.2020.102886 | L8: https://www.scopus.com/pages/publications/85079861440?origin=resultslist | M8: Article | N8: Final | P8: Scopus | Q8: 2-s2.0-85079861440 | R8: =COUNTIF( Papers!G:G, RAW_DATA!Q8 ) = 0 -> FALSE | S8: =(COUNTIF(B:B, B8) > 1 ) -> FALSE
A9: Rudin C.; Chen C.; Chen Z.; Huang H.; Semenova L.; Zhong C. | B9: Interpretable machine learning: Fundamental principles and 10 grand challenges | C9: 2022 | D9: Statistics Surveys | E9: 16 | H9: 1 | I9: 85 | J9: 684 | K9: 10.1214/21-SS133 | L9: https://www.scopus.com/pages/publications/85125573696?origin=resultslist | M9: Article | N9: Final | O9: All Open Access; Gold Open Access | P9: Scopus | Q9: 2-s2.0-85125573696 | R9: =COUNTIF( Papers!G:G, RAW_DATA!Q9 ) = 0 -> FALSE | S9: =(COUNTIF(B:B, B9) > 1 ) -> FALSE
A10: Asan O.; Bayrak A.E.; Choudhury A. | B10: Artificial Intelligence and Human Trust in Healthcare: Focus on Clinicians | C10: 2020 | D10: Journal of Medical Internet Research | E10: 22 | F10: 6 | G10: e15154 | J10: 604 | K10: 10.2196/15154 | L10: https://www.scopus.com/pages/publications/85086727009?origin=resultslist | M10: Review | N10: Final | O10: All Open Access; Gold Open Access; Green Open Access | P10: Scopus | Q10: 2-s2.0-85086727009 | R10: =COUNTIF( Papers!G:G, RAW_DATA!Q10 ) = 0 -> FALSE | S10: =(COUNTIF(B:B, B10) > 1 ) -> FALSE
A11: Hergeth S.; Lorenz L.; Vilimek R.; Krems J.F. | B11: Keep Your Scanners Peeled: Gaze Behavior as a Measure of Automation Trust during Highly Automated Driving | C11: 2016 | D11: Human Factors | E11: 58 | F11: 3 | H11: 509 | I11: 519 | J11: 311 | K11: 10.1177/0018720815625744 | L11: https://www.scopus.com/pages/publications/84962910809?origin=resultslist | M11: Article | N11: Final | P11: Scopus | Q11: 2-s2.0-84962910809 | R11: =COUNTIF( Papers!G:G, RAW_DATA!Q11 ) = 0 -> FALSE | S11: =(COUNTIF(B:B, B11) > 1 ) -> FALSE
A12: Honig S.; Oron-Gilad T. | B12: Understanding and resolving failures in human-robot interaction: Literature review and model development | C12: 2018 | D12: Frontiers in Psychology | E12: 9 | F12: JUN | G12: 861 | J12: 308 | K12: 10.3389/fpsyg.2018.00861 | L12: https://www.scopus.com/pages/publications/85048531596?origin=resultslist | M12: Review | N12: Final | O12: All Open Access; Gold Open Access; Green Open Access | P12: Scopus | Q12: 2-s2.0-85048531596 | R12: =COUNTIF( Papers!G:G, RAW_DATA!Q12 ) = 0 -> FALSE | S12: =(COUNTIF(B:B, B12) > 1 ) -> FALSE
A13: Carsten O.; Martens M.H. | B13: How can humans understand their automated cars? HMI principles, problems and solutions | C13: 2019 | D13: Cognition, Technology and Work | E13: 21 | F13: 1 | H13: 3 | I13: 20 | J13: 233 | K13: 10.1007/s10111-018-0484-0 | L13: https://www.scopus.com/pages/publications/85046726952?origin=resultslist | M13: Article | N13: Final | O13: All Open Access; Green Open Access; Hybrid Gold Open Access | P13: Scopus | Q13: 2-s2.0-85046726952 | R13: =COUNTIF( Papers!G:G, RAW_DATA!Q13 ) = 0 -> FALSE | S13: =(COUNTIF(B:B, B13) > 1 ) -> FALSE
A14: Vilone G.; Longo L. | B14: Notions of explainability and evaluation approaches for explainable artificial intelligence | C14: 2021 | D14: Information Fusion | E14: 76 | H14: 89 | I14: 106 | J14: 510 | K14: 10.1016/j.inffus.2021.05.009 | L14: https://www.scopus.com/pages/publications/85107637272?origin=resultslist | M14: Article | N14: Final | O14: All Open Access; Green Open Access; Hybrid Gold Open Access | P14: Scopus | Q14: 2-s2.0-85107637272 | R14: =COUNTIF( Papers!G:G, RAW_DATA!Q14 ) = 0 -> FALSE | S14: =(COUNTIF(B:B, B14) > 1 ) -> FALSE
A15: Pereira V.; Hadjielias E.; Christofi M.; Vrontis D. | B15: A systematic literature review on the impact of artificial intelligence on workplace outcomes: A multi-process perspective | C15: 2023 | D15: Human Resource Management Review | E15: 33 | F15: 1 | G15: 100857 | J15: 384 | K15: 10.1016/j.hrmr.2021.100857 | L15: https://www.scopus.com/pages/publications/85114687655?origin=resultslist | M15: Article | N15: Final | O15: All Open Access; Green Open Access | P15: Scopus | Q15: 2-s2.0-85114687655 | R15: =COUNTIF( Papers!G:G, RAW_DATA!Q15 ) = 0 -> FALSE | S15: =(COUNTIF(B:B, B15) > 1 ) -> FALSE
A16: Langer M.; Oster D.; Speith T.; Hermanns H.; Kästner L.; Schmidt E.; Sesing A.; Baum K. | B16: What do we want from Explainable Artificial Intelligence (XAI)? – A stakeholder perspective on XAI and a conceptual model guiding interdisciplinary XAI research | C16: 2021 | D16: Artificial Intelligence | E16: 296 | G16: 103473 | J16: 541 | K16: 10.1016/j.artint.2021.103473 | L16: https://www.scopus.com/pages/publications/85101531468?origin=resultslist | M16: Article | N16: Final | O16: All Open Access; Bronze Open Access; Green Open Access | P16: Scopus | Q16: 2-s2.0-85101531468 | R16: =COUNTIF( Papers!G:G, RAW_DATA!Q16 ) = 0 -> FALSE | S16: =(COUNTIF(B:B, B16) > 1 ) -> FALSE
A17: Chalmers D.; MacKenzie N.G.; Carter S. | B17: Artificial Intelligence and Entrepreneurship: Implications for Venture Creation in the Fourth Industrial Revolution | C17: 2021 | D17: Entrepreneurship: Theory and Practice | E17: 45 | F17: 5 | H17: 1028 | I17: 1053 | J17: 397 | K17: 10.1177/1042258720934581 | L17: https://www.scopus.com/pages/publications/85087930775?origin=resultslist | M17: Article | N17: Final | O17: All Open Access; Bronze Open Access; Green Open Access | P17: Scopus | Q17: 2-s2.0-85087930775 | R17: =COUNTIF( Papers!G:G, RAW_DATA!Q17 ) = 0 -> FALSE | S17: =(COUNTIF(B:B, B17) > 1 ) -> FALSE
A18: Chowdhury S.; Budhwar P.; Dey P.K.; Joel-Edgar S.; Abadie A. | B18: AI-employee collaboration and business performance: Integrating knowledge-based view, socio-technical systems and organisational socialisation framework | C18: 2022 | D18: Journal of Business Research | E18: 144 | H18: 31 | I18: 49 | J18: 365 | K18: 10.1016/j.jbusres.2022.01.069 | L18: https://www.scopus.com/pages/publications/85124046364?origin=resultslist | M18: Article | N18: Final | P18: Scopus | Q18: 2-s2.0-85124046364 | R18: =COUNTIF( Papers!G:G, RAW_DATA!Q18 ) = 0 -> FALSE | S18: =(COUNTIF(B:B, B18) > 1 ) -> FALSE
A19: Dellermann D.; Ebel P.; Söllner M.; Leimeister J.M. | B19: Hybrid Intelligence | C19: 2019 | D19: Business and Information Systems Engineering | E19: 61 | F19: 5 | H19: 637 | I19: 643 | J19: 581 | K19: 10.1007/s12599-019-00595-2 | L19: https://www.scopus.com/pages/publications/85069455009?origin=resultslist | M19: Article | N19: Final | O19: All Open Access; Green Open Access | P19: Scopus | Q19: 2-s2.0-85069455009 | R19: =COUNTIF( Papers!G:G, RAW_DATA!Q19 ) = 0 -> FALSE | S19: =(COUNTIF(B:B, B19) > 1 ) -> FALSE
A20: Man Tang P.; Koopman J.; McClean S.T.; Zhang J.H.; Hon Li C.; de Cremer D.; Lu Y.; Stewart Ng C.T. | B20: WHEN CONSCIENTIOUS EMPLOYEES MEET INTELLIGENT MACHINES: AN INTEGRATIVE APPROACH INSPIRED BY COMPLEMENTARITY THEORY AND ROLE THEORY | C20: 2022 | D20: Academy of Management Journal | E20: 65 | F20: 3 | H20: 1019 | I20: 1054 | J20: 230 | K20: 10.5465/AMJ.2020.1516 | L20: https://www.scopus.com/pages/publications/85135124659?origin=resultslist | M20: Article | N20: Final | P20: Scopus | Q20: 2-s2.0-85135124659 | R20: =COUNTIF( Papers!G:G, RAW_DATA!Q20 ) = 0 -> FALSE | S20: =(COUNTIF(B:B, B20) > 1 ) -> FALSE
A21: Mirbabaie M.; Brünker F.; Möllmann Frick N.R.J.; Stieglitz S. | B21: The rise of artificial intelligence – understanding the AI identity threat at the workplace | C21: 2022 | D21: Electronic Markets | E21: 32 | F21: 1 | H21: 73 | I21: 99 | J21: 259 | K21: 10.1007/s12525-021-00496-x | L21: https://www.scopus.com/pages/publications/85116415765?origin=resultslist | M21: Article | N21: Final | O21: All Open Access; Green Open Access; Hybrid Gold Open Access | P21: Scopus | Q21: 2-s2.0-85116415765 | R21: =COUNTIF( Papers!G:G, RAW_DATA!Q21 ) = 0 -> FALSE | S21: =(COUNTIF(B:B, B21) > 1 ) -> FALSE
A22: Bedué P.; Fritzsche A. | B22: Can we trust AI? An empirical investigation of trust requirements and guide to successful AI adoption | C22: 2022 | D22: Journal of Enterprise Information Management | E22: 35 | F22: 2 | H22: 530 | I22: 549 | J22: 250 | K22: 10.1108/JEIM-06-2020-0233 | L22: https://www.scopus.com/pages/publications/85106282628?origin=resultslist | M22: Article | N22: Final | P22: Scopus | Q22: 2-s2.0-85106282628 | R22: =COUNTIF( Papers!G:G, RAW_DATA!Q22 ) = 0 -> FALSE | S22: =(COUNTIF(B:B, B22) > 1 ) -> FALSE
A23: Parent-Rocheleau X.; Parker S.K. | B23: Algorithms as work designers: How algorithmic management influences the design of jobs | C23: 2022 | D23: Human Resource Management Review | E23: 32 | F23: 3 | G23: 100838 | J23: 330 | K23: 10.1016/j.hrmr.2021.100838 | L23: https://www.scopus.com/pages/publications/85105550128?origin=resultslist | M23: Article | N23: Final | O23: All Open Access; Bronze Open Access; Green Open Access | P23: Scopus | Q23: 2-s2.0-85105550128 | R23: =COUNTIF( Papers!G:G, RAW_DATA!Q23 ) = 0 -> FALSE | S23: =(COUNTIF(B:B, B23) > 1 ) -> FALSE
A24: Hayes B.; Shah J.A. | B24: Improving Robot Controller Transparency Through Autonomous Policy Explanation | C24: 2017 | D24: ACM/IEEE International Conference on Human-Robot Interaction | E24: Part F127194 | H24: 303 | I24: 312 | J24: 234 | K24: 10.1145/2909824.3020233 | L24: https://www.scopus.com/pages/publications/85021787797?origin=resultslist | M24: Conference paper | N24: Final | O24: All Open Access; Green Open Access | P24: Scopus | Q24: 2-s2.0-85021787797 | R24: =COUNTIF( Papers!G:G, RAW_DATA!Q24 ) = 0 -> FALSE | S24: =(COUNTIF(B:B, B24) > 1 ) -> FALSE
A25: Dudley J.J.; Kristensson P.O. | B25: A review of user interface design for interactive machine learning | C25: 2018 | D25: ACM Transactions on Interactive Intelligent Systems | E25: 8 | F25: 2 | G25: 8 | J25: 292 | K25: 10.1145/3185517 | L25: https://www.scopus.com/pages/publications/85058625902?origin=resultslist | M25: Review | N25: Final | O25: All Open Access; Green Open Access | P25: Scopus | Q25: 2-s2.0-85058625902 | R25: =COUNTIF( Papers!G:G, RAW_DATA!Q25 ) = 0 -> FALSE | S25: =(COUNTIF(B:B, B25) > 1 ) -> FALSE
A26: Chowdhury S.; Dey P.; Joel-Edgar S.; Bhattacharya S.; Rodriguez-Espindola O.; Abadie A.; Truong L. | B26: Unlocking the value of artificial intelligence in human resource management through AI capability framework | C26: 2023 | D26: Human Resource Management Review | E26: 33 | F26: 1 | G26: 100899 | J26: 719 | K26: 10.1016/j.hrmr.2022.100899 | L26: https://www.scopus.com/pages/publications/85127325455?origin=resultslist | M26: Article | N26: Final | O26: All Open Access; Green Open Access | P26: Scopus | Q26: 2-s2.0-85127325455 | R26: =COUNTIF( Papers!G:G, RAW_DATA!Q26 ) = 0 -> FALSE | S26: =(COUNTIF(B:B, B26) > 1 ) -> FALSE
A27: Chiou E.K.; Lee J.D. | B27: Trusting Automation: Designing for Responsivity and Resilience | C27: 2023 | D27: Human Factors | E27: 65 | F27: 1 | H27: 137 | I27: 165 | J27: 234 | K27: 10.1177/00187208211009995 | L27: https://www.scopus.com/pages/publications/85104981249?origin=resultslist | M27: Article | N27: Final | P27: Scopus | Q27: 2-s2.0-85104981249 | R27: =COUNTIF( Papers!G:G, RAW_DATA!Q27 ) = 0 -> FALSE | S27: =(COUNTIF(B:B, B27) > 1 ) -> FALSE
A28: Liu K.; Tao D. | B28: The roles of trust, personalization, loss of privacy, and anthropomorphism in public acceptance of smart healthcare services | C28: 2022 | D28: Computers in Human Behavior | E28: 127 | G28: 107026 | J28: 363 | K28: 10.1016/j.chb.2021.107026 | L28: https://www.scopus.com/pages/publications/85115048327?origin=resultslist | M28: Article | N28: Final | P28: Scopus | Q28: 2-s2.0-85115048327 | R28: =COUNTIF( Papers!G:G, RAW_DATA!Q28 ) = 0 -> FALSE | S28: =(COUNTIF(B:B, B28) > 1 ) -> FALSE
A29: Yam K.C.; Tang P.M.; Jackson J.C.; Su R.; Gray K. | B29: The Rise of Robots Increases Job Insecurity and Maladaptive Workplace Behaviors: Multimethod Evidence | C29: 2022 | D29: Journal of Applied Psychology | E29: 108 | F29: 5 | H29: 850 | I29: 870 | J29: 244 | K29: 10.1037/apl0001045 | L29: https://www.scopus.com/pages/publications/85140762473?origin=resultslist | M29: Article | N29: Final | P29: Scopus | Q29: 2-s2.0-85140762473 | R29: =COUNTIF( Papers!G:G, RAW_DATA!Q29 ) = 0 -> FALSE | S29: =(COUNTIF(B:B, B29) > 1 ) -> FALSE
A30: Kohn S.C.; de Visser E.J.; Wiese E.; Lee Y.-C.; Shaw T.H. | B30: Measurement of Trust in Automation: A Narrative Review and Reference Guide | C30: 2021 | D30: Frontiers in Psychology | E30: 12 | G30: 604977 | J30: 253 | K30: 10.3389/fpsyg.2021.604977 | L30: https://www.scopus.com/pages/publications/85118576621?origin=resultslist | M30: Review | N30: Final | O30: All Open Access; Gold Open Access; Green Open Access | P30: Scopus | Q30: 2-s2.0-85118576621 | R30: =COUNTIF( Papers!G:G, RAW_DATA!Q30 ) = 0 -> FALSE | S30: =(COUNTIF(B:B, B30) > 1 ) -> FALSE
A31: Hengstler M.; Enkel E.; Duelli S. | B31: Applied artificial intelligence and trust-The case of autonomous vehicles and medical assistance devices | C31: 2016 | D31: Technological Forecasting and Social Change | E31: 105 | H31: 105 | I31: 120 | J31: 557 | K31: 10.1016/j.techfore.2015.12.014 | L31: https://www.scopus.com/pages/publications/84957895151?origin=resultslist | M31: Article | N31: Final | P31: Scopus | Q31: 2-s2.0-84957895151 | R31: =COUNTIF( Papers!G:G, RAW_DATA!Q31 ) = 0 -> FALSE | S31: =(COUNTIF(B:B, B31) > 1 ) -> FALSE
A32: Bach T.A.; Khan A.; Hallock H.; Beltrão G.; Sousa S. | B32: A Systematic Literature Review of User Trust in AI-Enabled Systems: An HCI Perspective | C32: 2024 | D32: International Journal of Human-Computer Interaction | E32: 40 | F32: 5 | H32: 1251 | I32: 1266 | J32: 239 | K32: 10.1080/10447318.2022.2138826 | L32: https://www.scopus.com/pages/publications/85141953140?origin=resultslist | M32: Article | N32: Final | O32: All Open Access; Bronze Open Access; Green Open Access | P32: Scopus | Q32: 2-s2.0-85141953140 | R32: =COUNTIF( Papers!G:G, RAW_DATA!Q32 ) = 0 -> FALSE | S32: =(COUNTIF(B:B, B32) > 1 ) -> FALSE
A33: Sun W.; Bocchini P.; Davison B.D. | B33: Applications of artificial intelligence for disaster management | C33: 2020 | D33: Natural Hazards | E33: 103 | F33: 3 | H33: 2631 | I33: 2689 | J33: 376 | K33: 10.1007/s11069-020-04124-3 | L33: https://www.scopus.com/pages/publications/85087516664?origin=resultslist | M33: Review | N33: Final | P33: Scopus | Q33: 2-s2.0-85087516664 | R33: =COUNTIF( Papers!G:G, RAW_DATA!Q33 ) = 0 -> FALSE | S33: =(COUNTIF(B:B, B33) > 1 ) -> FALSE
A34: Glikson E.; Woolley A.W. | B34: Human trust in artificial intelligence: Review of empirical research | C34: 2020 | D34: Academy of Management Annals | E34: 14 | F34: 2 | H34: 627 | I34: 660 | J34: 1836 | K34: 10.5465/annals.2018.0057 | L34: https://www.scopus.com/pages/publications/85087295894?origin=resultslist | M34: Article | N34: Final | P34: Scopus | Q34: 2-s2.0-85087295894 | R34: =COUNTIF( Papers!G:G, RAW_DATA!Q34 ) = 0 -> FALSE | S34: =(COUNTIF(B:B, B34) > 1 ) -> FALSE
A35: Xu Z.; Zhang K.; Min H.; Wang Z.; Zhao X.; Liu P. | B35: What drives people to accept automated vehicles? Findings from a field experiment | C35: 2018 | D35: Transportation Research Part C: Emerging Technologies | E35: 95 | H35: 320 | I35: 334 | J35: 580 | K35: 10.1016/j.trc.2018.07.024 | L35: https://www.scopus.com/pages/publications/85050653532?origin=resultslist | M35: Article | N35: Final | P35: Scopus | Q35: 2-s2.0-85050653532 | R35: =COUNTIF( Papers!G:G, RAW_DATA!Q35 ) = 0 -> FALSE | S35: =(COUNTIF(B:B, B35) > 1 ) -> FALSE
A36: Haleem A.; Javaid M.; Asim Qadri M.; Pratap Singh R.; Suman R. | B36: Artificial intelligence (AI) applications for marketing: A literature-based study | C36: 2022 | D36: International Journal of Intelligent Networks | E36: 3 | H36: 119 | I36: 132 | J36: 738 | K36: 10.1016/j.ijin.2022.08.005 | L36: https://www.scopus.com/pages/publications/85137403442?origin=resultslist | M36: Review | N36: Final | O36: All Open Access; Gold Open Access; Green Open Access | P36: Scopus | Q36: 2-s2.0-85137403442 | R36: =COUNTIF( Papers!G:G, RAW_DATA!Q36 ) = 0 -> FALSE | S36: =(COUNTIF(B:B, B36) > 1 ) -> FALSE
A37: Mathur M.B.; Reichling D.B. | B37: Navigating a social world with robot partners: A quantitative cartography of the Uncanny Valley | C37: 2016 | D37: Cognition | E37: 146 | H37: 22 | I37: 32 | J37: 360 | K37: 10.1016/j.cognition.2015.09.008 | L37: https://www.scopus.com/pages/publications/84942154696?origin=resultslist | M37: Article | N37: Final | O37: All Open Access; Hybrid Gold Open Access | P37: Scopus | Q37: 2-s2.0-84942154696 | R37: =COUNTIF( Papers!G:G, RAW_DATA!Q37 ) = 0 -> FALSE | S37: =(COUNTIF(B:B, B37) > 1 ) -> FALSE
A38: Abdul A.; Vermeulen J.; Wang D.; Lim B.Y.; Kankanhalli M. | B38: Trends and trajectories for explainable, accountable and intelligible systems: An HCI research agenda | C38: 2018 | D38: Conference on Human Factors in Computing Systems - Proceedings | E38: 2018-April | J38: 639 | K38: 10.1145/3173574.3174156 | L38: https://www.scopus.com/pages/publications/85044532871?origin=resultslist | M38: Conference paper | N38: Final | P38: Scopus | Q38: 2-s2.0-85044532871 | R38: =COUNTIF( Papers!G:G, RAW_DATA!Q38 ) = 0 -> FALSE | S38: =(COUNTIF(B:B, B38) > 1 ) -> FALSE
A39: Zhang Y.; Xiong F.; Xie Y.; Fan X.; Gu H. | B39: The Impact of Artificial Intelligence and Blockchain on the Accounting Profession | C39: 2020 | D39: IEEE Access | E39: 8 | G39: 9110603 | H39: 110461 | I39: 110477 | J39: 233 | K39: 10.1109/ACCESS.2020.3000505 | L39: https://www.scopus.com/pages/publications/85087542875?origin=resultslist | M39: Article | N39: Final | O39: All Open Access; Gold Open Access; Green Open Access | P39: Scopus | Q39: 2-s2.0-85087542875 | R39: =COUNTIF( Papers!G:G, RAW_DATA!Q39 ) = 0 -> FALSE | S39: =(COUNTIF(B:B, B39) > 1 ) -> FALSE
A40: Nastjuk I.; Herrenkind B.; Marrone M.; Brendel A.B.; Kolbe L.M. | B40: What drives the acceptance of autonomous driving? An investigation of acceptance factors from an end-user's perspective | C40: 2020 | D40: Technological Forecasting and Social Change | E40: 161 | G40: 120319 | J40: 302 | K40: 10.1016/j.techfore.2020.120319 | L40: https://www.scopus.com/pages/publications/85091505828?origin=resultslist | M40: Article | N40: Final | O40: All Open Access; Hybrid Gold Open Access | P40: Scopus | Q40: 2-s2.0-85091505828 | R40: =COUNTIF( Papers!G:G, RAW_DATA!Q40 ) = 0 -> FALSE | S40: =(COUNTIF(B:B, B40) > 1 ) -> FALSE
A41: Kuziemski M.; Misuraca G. | B41: AI governance in the public sector: Three tales from the frontiers of automated decision-making in democratic settings | C41: 2020 | D41: Telecommunications Policy | E41: 44 | F41: 6 | G41: 101976 | J41: 461 | K41: 10.1016/j.telpol.2020.101976 | L41: https://www.scopus.com/pages/publications/85084122224?origin=resultslist | M41: Article | N41: Final | O41: All Open Access; Green Open Access | P41: Scopus | Q41: 2-s2.0-85084122224 | R41: =COUNTIF( Papers!G:G, RAW_DATA!Q41 ) = 0 -> FALSE | S41: =(COUNTIF(B:B, B41) > 1 ) -> FALSE
A42: Ruff L.; Kauffmann J.R.; Vandermeulen R.A.; Montavon G.; Samek W.; Kloft M.; Dietterich T.G.; Muller K.-R. | B42: A Unifying Review of Deep and Shallow Anomaly Detection | C42: 2021 | D42: Proceedings of the IEEE | E42: 109 | F42: 5 | G42: 9347460 | H42: 756 | I42: 795 | J42: 892 | K42: 10.1109/JPROC.2021.3052449 | L42: https://www.scopus.com/pages/publications/85100863824?origin=resultslist | M42: Article | N42: Final | O42: All Open Access; Green Open Access; Hybrid Gold Open Access | P42: Scopus | Q42: 2-s2.0-85100863824 | R42: =COUNTIF( Papers!G:G, RAW_DATA!Q42 ) = 0 -> FALSE | S42: =(COUNTIF(B:B, B42) > 1 ) -> FALSE
A43: Haefner N.; Wincent J.; Parida V.; Gassmann O. | B43: Artificial intelligence and innovation management: A review, framework, and research agenda✰ | C43: 2021 | D43: Technological Forecasting and Social Change | E43: 162 | G43: 120392 | J43: 788 | K43: 10.1016/j.techfore.2020.120392 | L43: https://www.scopus.com/pages/publications/85092748091?origin=resultslist | M43: Article | N43: Final | O43: All Open Access; Hybrid Gold Open Access | P43: Scopus | Q43: 2-s2.0-85092748091 | R43: =COUNTIF( Papers!G:G, RAW_DATA!Q43 ) = 0 -> FALSE | S43: =(COUNTIF(B:B, B43) > 1 ) -> FALSE
A44: Jacovi A.; Marasović A.; Miller T.; Goldberg Y. | B44: Formalizing trust in artificial intelligence: Prerequisites, causes and goals of human trust in AI | C44: 2021 | D44: FAccT 2021 - Proceedings of the 2021 ACM Conference on Fairness, Accountability, and Transparency | G44: 3445923 | H44: 624 | I44: 635 | J44: 466 | K44: 10.1145/3442188.3445923 | L44: https://www.scopus.com/pages/publications/85102636939?origin=resultslist | M44: Conference paper | N44: Final | P44: Scopus | Q44: 2-s2.0-85102636939 | R44: =COUNTIF( Papers!G:G, RAW_DATA!Q44 ) = 0 -> FALSE | S44: =(COUNTIF(B:B, B44) > 1 ) -> FALSE
A45: Robinette P.; Li W.; Allen R.; Howard A.M.; Wagner A.R. | B45: Overtrust of robots in emergency evacuation scenarios | C45: 2016 | D45: ACM/IEEE International Conference on Human-Robot Interaction | E45: 2016-April | G45: 7451740 | H45: 101 | I45: 108 | J45: 398 | K45: 10.1109/HRI.2016.7451740 | L45: https://www.scopus.com/pages/publications/84964846793?origin=resultslist | M45: Conference paper | N45: Final | P45: Scopus | Q45: 2-s2.0-84964846793 | R45: =COUNTIF( Papers!G:G, RAW_DATA!Q45 ) = 0 -> FALSE | S45: =(COUNTIF(B:B, B45) > 1 ) -> FALSE
A46: Chi O.H.; Jia S.; Li Y.; Gursoy D. | B46: Developing a formative scale to measure consumers’ trust toward interaction with artificially intelligent (AI) social robots in service delivery | C46: 2021 | D46: Computers in Human Behavior | E46: 118 | G46: 106700 | J46: 260 | K46: 10.1016/j.chb.2021.106700 | L46: https://www.scopus.com/pages/publications/85099979829?origin=resultslist | M46: Article | N46: Final | P46: Scopus | Q46: 2-s2.0-85099979829 | R46: =COUNTIF( Papers!G:G, RAW_DATA!Q46 ) = 0 -> FALSE | S46: =(COUNTIF(B:B, B46) > 1 ) -> FALSE
A47: Kaur D.; Uslu S.; Rittichier K.J.; Durresi A. | B47: Trustworthy Artificial Intelligence: A Review | C47: 2023 | D47: ACM Computing Surveys | E47: 55 | F47: 2 | G47: 3491209 | J47: 603 | K47: 10.1145/3491209 | L47: https://www.scopus.com/pages/publications/85128190943?origin=resultslist | M47: Review | N47: Final | P47: Scopus | Q47: 2-s2.0-85128190943 | R47: =COUNTIF( Papers!G:G, RAW_DATA!Q47 ) = 0 -> FALSE | S47: =(COUNTIF(B:B, B47) > 1 ) -> FALSE
A48: König M.; Neumayr L. | B48: Users’ resistance towards radical innovations: The case of the self-driving car | C48: 2017 | D48: Transportation Research Part F: Traffic Psychology and Behaviour | E48: 44 | H48: 42 | I48: 52 | J48: 372 | K48: 10.1016/j.trf.2016.10.013 | L48: https://www.scopus.com/pages/publications/84995549556?origin=resultslist | M48: Article | N48: Final | P48: Scopus | Q48: 2-s2.0-84995549556 | R48: =COUNTIF( Papers!G:G, RAW_DATA!Q48 ) = 0 -> FALSE | S48: =(COUNTIF(B:B, B48) > 1 ) -> FALSE
A49: Albahri A.S.; Duhaim A.M.; Fadhel M.A.; Alnoor A.; Baqer N.S.; Alzubaidi L.; Albahri O.S.; Alamoodi A.H.; Bai J.; Salhi A.; Santamaría J.; Ouyang C.; Gupta A.; Gu Y.; Deveci M. | B49: A systematic review of trustworthy and explainable artificial intelligence in healthcare: Assessment of quality, bias risk, and data fusion | C49: 2023 | D49: Information Fusion | E49: 96 | H49: 156 | I49: 191 | J49: 595 | K49: 10.1016/j.inffus.2023.03.008 | L49: https://www.scopus.com/pages/publications/85151265419?origin=resultslist | M49: Article | N49: Final | P49: Scopus | Q49: 2-s2.0-85151265419 | R49: =COUNTIF( Papers!G:G, RAW_DATA!Q49 ) = 0 -> FALSE | S49: =(COUNTIF(B:B, B49) > 1 ) -> FALSE
A50: Laux J.; Wachter S.; Mittelstadt B. | B50: Trustworthy artificial intelligence and the European Union AI act: On the conflation of trustworthiness and acceptability of risk | C50: 2024 | D50: Regulation and Governance | E50: 18 | F50: 1 | H50: 3 | I50: 32 | J50: 268 | K50: 10.1111/rego.12512 | L50: https://www.scopus.com/pages/publications/85147512970?origin=resultslist | M50: Article | N50: Final | O50: All Open Access; Green Open Access; Hybrid Gold Open Access | P50: Scopus | Q50: 2-s2.0-85147512970 | R50: =COUNTIF( Papers!G:G, RAW_DATA!Q50 ) = 0 -> FALSE | S50: =(COUNTIF(B:B, B50) > 1 ) -> FALSE
A51: Hancock P.A.; Nourbakhsh I.; Stewart J. | B51: On the future of transportation in an era of automated and autonomous vehicles | C51: 2019 | D51: Proceedings of the National Academy of Sciences of the United States of America | E51: 116 | F51: 16 | H51: 7684 | I51: 7691 | J51: 265 | K51: 10.1073/pnas.1805770115 | L51: https://www.scopus.com/pages/publications/85064355391?origin=resultslist | M51: Article | N51: Final | O51: All Open Access; Bronze Open Access | P51: Scopus | Q51: 2-s2.0-85064355391 | R51: =COUNTIF( Papers!G:G, RAW_DATA!Q51 ) = 0 -> FALSE | S51: =(COUNTIF(B:B, B51) > 1 ) -> FALSE
A52: Ozmen Garibay O.; Winslow B.; Andolina S.; Antona M.; Bodenschatz A.; Coursaris C.; Falco G.; Fiore S.M.; Garibay I.; Grieman K.; Havens J.C.; Jirotka M.; Kacorri H.; Karwowski W.; Kider J.; Konstan J.; Koon S.; Lopez-Gonzalez M.; Maifeld-Carucci I.; McGregor S.; Salvendy G.; Shneiderman B.; Stephanidis C.; Strobel C.; Ten Holter C.; Xu W. | B52: Six Human-Centered Artificial Intelligence Grand Challenges | C52: 2023 | D52: International Journal of Human-Computer Interaction | E52: 39 | F52: 3 | H52: 391 | I52: 437 | J52: 392 | K52: 10.1080/10447318.2022.2153320 | L52: https://www.scopus.com/pages/publications/85145502740?origin=resultslist | M52: Article | N52: Final | O52: All Open Access; Green Open Access; Hybrid Gold Open Access | P52: Scopus | Q52: 2-s2.0-85145502740 | R52: =COUNTIF( Papers!G:G, RAW_DATA!Q52 ) = 0 -> FALSE | S52: =(COUNTIF(B:B, B52) > 1 ) -> FALSE
A53: Hermann E. | B53: Leveraging Artificial Intelligence in Marketing for Social Good—An Ethical Perspective | C53: 2022 | D53: Journal of Business Ethics | E53: 179 | F53: 1 | H53: 43 | I53: 61 | J53: 277 | K53: 10.1007/s10551-021-04843-y | L53: https://www.scopus.com/pages/publications/85106476454?origin=resultslist | M53: Article | N53: Final | O53: All Open Access; Green Open Access; Hybrid Gold Open Access | P53: Scopus | Q53: 2-s2.0-85106476454 | R53: =COUNTIF( Papers!G:G, RAW_DATA!Q53 ) = 0 -> FALSE | S53: =(COUNTIF(B:B, B53) > 1 ) -> FALSE
A54: Katzenbach C.; Ulbricht L. | B54: Algorithmic governance | C54: 2019 | D54: Internet Policy Review | E54: 8 | F54: 4 | J54: 231 | K54: 10.14763/2019.4.1424 | L54: https://www.scopus.com/pages/publications/85077848137?origin=resultslist | M54: Article | N54: Final | O54: All Open Access; Gold Open Access; Green Open Access | P54: Scopus | Q54: 2-s2.0-85077848137 | R54: =COUNTIF( Papers!G:G, RAW_DATA!Q54 ) = 0 -> FALSE | S54: =(COUNTIF(B:B, B54) > 1 ) -> FALSE
A55: Omrani N.; Rivieccio G.; Fiore U.; Schiavone F.; Agreda S.G. | B55: To trust or not to trust? An assessment of trust in AI-based systems: Concerns, ethics and contexts | C55: 2022 | D55: Technological Forecasting and Social Change | E55: 181 | G55: 121763 | J55: 221 | K55: 10.1016/j.techfore.2022.121763 | L55: https://www.scopus.com/pages/publications/85130877872?origin=resultslist | M55: Article | N55: Final | P55: Scopus | Q55: 2-s2.0-85130877872 | R55: =COUNTIF( Papers!G:G, RAW_DATA!Q55 ) = 0 -> FALSE | S55: =(COUNTIF(B:B, B55) > 1 ) -> FALSE
A56: Toreini E.; Aitken M.; Coopamootoo K.; Elliott K.; Zelaya C.G.; van Moorsel A. | B56: The relationship between trust in AI and trustworthy machine learning technologies | C56: 2020 | D56: FAT* 2020 - Proceedings of the 2020 Conference on Fairness, Accountability, and Transparency | H56: 272 | I56: 283 | J56: 254 | K56: 10.1145/3351095.3372834 | L56: https://www.scopus.com/pages/publications/85079632241?origin=resultslist | M56: Conference paper | N56: Final | O56: All Open Access; Green Open Access | P56: Scopus | Q56: 2-s2.0-85079632241 | R56: =COUNTIF( Papers!G:G, RAW_DATA!Q56 ) = 0 -> FALSE | S56: =(COUNTIF(B:B, B56) > 1 ) -> FALSE
A57: Choung H.; David P.; Ross A. | B57: Trust in AI and Its Role in the Acceptance of AI Technologies | C57: 2023 | D57: International Journal of Human-Computer Interaction | E57: 39 | F57: 9 | H57: 1727 | I57: 1739 | J57: 593 | K57: 10.1080/10447318.2022.2050543 | L57: https://www.scopus.com/pages/publications/85129401047?origin=resultslist | M57: Article | N57: Final | O57: All Open Access; Green Open Access | P57: Scopus | Q57: 2-s2.0-85129401047 | R57: =COUNTIF( Papers!G:G, RAW_DATA!Q57 ) = 0 -> FALSE | S57: =(COUNTIF(B:B, B57) > 1 ) -> FALSE
A58: Dixit V.V.; Chand S.; Nair D.J. | B58: Autonomous vehicles: Disengagements, accidents and reaction times | C58: 2016 | D58: PLoS ONE | E58: 11 | F58: 12 | G58: e0168054 | J58: 342 | K58: 10.1371/journal.pone.0168054 | L58: https://www.scopus.com/pages/publications/85006900493?origin=resultslist | M58: Article | N58: Final | O58: All Open Access; Gold Open Access; Green Open Access | P58: Scopus | Q58: 2-s2.0-85006900493 | R58: =COUNTIF( Papers!G:G, RAW_DATA!Q58 ) = 0 -> FALSE | S58: =(COUNTIF(B:B, B58) > 1 ) -> FALSE
A59: Jing P.; Xu G.; Chen Y.; Shi Y.; Zhan F. | B59: The determinants behind the acceptance of autonomous vehicles: A systematic review | C59: 2020 | D59: Sustainability (Switzerland) | E59: 12 | F59: 5 | G59: 1719 | J59: 295 | K59: 10.3390/su12051719 | L59: https://www.scopus.com/pages/publications/85082878572?origin=resultslist | M59: Review | N59: Final | O59: All Open Access; Gold Open Access; Green Open Access | P59: Scopus | Q59: 2-s2.0-85082878572 | R59: =COUNTIF( Papers!G:G, RAW_DATA!Q59 ) = 0 -> FALSE | S59: =(COUNTIF(B:B, B59) > 1 ) -> FALSE
A60: Zhang J.; Zhang Z.-M. | B60: Ethics and governance of trustworthy medical artificial intelligence | C60: 2023 | D60: BMC Medical Informatics and Decision Making | E60: 23 | F60: 1 | G60: 7 | J60: 351 | K60: 10.1186/s12911-023-02103-9 | L60: https://www.scopus.com/pages/publications/85146278182?origin=resultslist | M60: Article | N60: Final | O60: All Open Access; Gold Open Access; Green Open Access | P60: Scopus | Q60: 2-s2.0-85146278182 | R60: =COUNTIF( Papers!G:G, RAW_DATA!Q60 ) = 0 -> FALSE | S60: =(COUNTIF(B:B, B60) > 1 ) -> FALSE
A61: Zirar A.; Ali S.I.; Islam N. | B61: Worker and workplace Artificial Intelligence (AI) coexistence: Emerging themes and research agenda | C61: 2023 | D61: Technovation | E61: 124 | G61: 102747 | J61: 289 | K61: 10.1016/j.technovation.2023.102747 | L61: https://www.scopus.com/pages/publications/85150032477?origin=resultslist | M61: Article | N61: Final | O61: All Open Access; Green Open Access; Hybrid Gold Open Access | P61: Scopus | Q61: 2-s2.0-85150032477 | R61: =COUNTIF( Papers!G:G, RAW_DATA!Q61 ) = 0 -> FALSE | S61: =(COUNTIF(B:B, B61) > 1 ) -> FALSE
A62: Jarrahi M.H.; Newlands G.; Lee M.K.; Wolf C.T.; Kinder E.; Sutherland W. | B62: Algorithmic management in a work context | C62: 2021 | D62: Big Data and Society | E62: 8 | F62: 2 | J62: 317 | K62: 10.1177/20539517211020332 | L62: https://www.scopus.com/pages/publications/85109319306?origin=resultslist | M62: Article | N62: Final | O62: All Open Access; Gold Open Access; Green Open Access | P62: Scopus | Q62: 2-s2.0-85109319306 | R62: =COUNTIF( Papers!G:G, RAW_DATA!Q62 ) = 0 -> FALSE | S62: =(COUNTIF(B:B, B62) > 1 ) -> FALSE
A63: Hasan R.; Shams R.; Rahman M. | B63: Consumer trust and perceived risk for voice-controlled artificial intelligence: The case of Siri | C63: 2021 | D63: Journal of Business Research | E63: 131 | H63: 591 | I63: 597 | J63: 271 | K63: 10.1016/j.jbusres.2020.12.012 | L63: https://www.scopus.com/pages/publications/85098163651?origin=resultslist | M63: Article | N63: Final | O63: All Open Access; Bronze Open Access; Green Open Access | P63: Scopus | Q63: 2-s2.0-85098163651 | R63: =COUNTIF( Papers!G:G, RAW_DATA!Q63 ) = 0 -> FALSE | S63: =(COUNTIF(B:B, B63) > 1 ) -> FALSE
A64: Suresh H.; Guttag J. | B64: A Framework for Understanding Sources of Harm throughout the Machine Learning Life Cycle | C64: 2021 | D64: ACM International Conference Proceeding Series | G64: 3483305 | J64: 332 | K64: 10.1145/3465416.3483305 | L64: https://www.scopus.com/pages/publications/85119301669?origin=resultslist | M64: Conference paper | N64: Final | O64: All Open Access; Gold Open Access; Green Open Access | P64: Scopus | Q64: 2-s2.0-85119301669 | R64: =COUNTIF( Papers!G:G, RAW_DATA!Q64 ) = 0 -> FALSE | S64: =(COUNTIF(B:B, B64) > 1 ) -> FALSE
A65: de Visser E.J.; Peeters M.M.M.; Jung M.F.; Kohn S.; Shaw T.H.; Pak R.; Neerincx M.A. | B65: Towards a Theory of Longitudinal Trust Calibration in Human–Robot Teams | C65: 2020 | D65: International Journal of Social Robotics | E65: 12 | F65: 2 | H65: 459 | I65: 478 | J65: 362 | K65: 10.1007/s12369-019-00596-x | L65: https://www.scopus.com/pages/publications/85084924592?origin=resultslist | M65: Article | N65: Final | P65: Scopus | Q65: 2-s2.0-85084924592 | R65: =COUNTIF( Papers!G:G, RAW_DATA!Q65 ) = 0 -> FALSE | S65: =(COUNTIF(B:B, B65) > 1 ) -> FALSE
A66: Park S. | B66: Multifaceted trust in tourism service robots | C66: 2020 | D66: Annals of Tourism Research | E66: 81 | G66: 102888 | J66: 255 | K66: 10.1016/j.annals.2020.102888 | L66: https://www.scopus.com/pages/publications/85080112789?origin=resultslist | M66: Article | N66: Final | P66: Scopus | Q66: 2-s2.0-85080112789 | R66: =COUNTIF( Papers!G:G, RAW_DATA!Q66 ) = 0 -> FALSE | S66: =(COUNTIF(B:B, B66) > 1 ) -> FALSE
A67: Zhang Y.; Vera Liao Q.; Bellamy R.K.E. | B67: Efect of confidence and explanation on accuracy and trust calibration in AI-assisted decision making | C67: 2020 | D67: FAT* 2020 - Proceedings of the 2020 Conference on Fairness, Accountability, and Transparency | H67: 295 | I67: 305 | J67: 689 | K67: 10.1145/3351095.3372852 | L67: https://www.scopus.com/pages/publications/85079608746?origin=resultslist | M67: Conference paper | N67: Final | O67: All Open Access; Green Open Access | P67: Scopus | Q67: 2-s2.0-85079608746 | R67: =COUNTIF( Papers!G:G, RAW_DATA!Q67 ) = 0 -> FALSE | S67: =(COUNTIF(B:B, B67) > 1 ) -> FALSE
A68: Ameen N.; Tarhini A.; Reppel A.; Anand A. | B68: Customer experiences in the age of artificial intelligence | C68: 2021 | D68: Computers in Human Behavior | E68: 114 | G68: 106548 | J68: 617 | K68: 10.1016/j.chb.2020.106548 | L68: https://www.scopus.com/pages/publications/85090737455?origin=resultslist | M68: Article | N68: Final | O68: All Open Access; Green Open Access | P68: Scopus | Q68: 2-s2.0-85090737455 | R68: =COUNTIF( Papers!G:G, RAW_DATA!Q68 ) = 0 -> FALSE | S68: =(COUNTIF(B:B, B68) > 1 ) -> FALSE
A69: Siau K.; Wang W. | B69: Artificial intelligence (AI) Ethics: Ethics of AI and ethical AI | C69: 2020 | D69: Journal of Database Management | E69: 31 | F69: 2 | H69: 74 | I69: 87 | J69: 449 | K69: 10.4018/JDM.2020040105 | L69: https://www.scopus.com/pages/publications/85097225749?origin=resultslist | M69: Review | N69: Final | P69: Scopus | Q69: 2-s2.0-85097225749 | R69: =COUNTIF( Papers!G:G, RAW_DATA!Q69 ) = 0 -> FALSE | S69: =(COUNTIF(B:B, B69) > 1 ) -> FALSE
A70: Habbal A.; Ali M.K.; Abuzaraida M.A. | B70: Artificial Intelligence Trust, Risk and Security Management (AI TRiSM): Frameworks, applications, challenges and future research directions | C70: 2024 | D70: Expert Systems with Applications | E70: 240 | G70: 122442 | J70: 290 | K70: 10.1016/j.eswa.2023.122442 | L70: https://www.scopus.com/pages/publications/85179498220?origin=resultslist | M70: Review | N70: Final | P70: Scopus | Q70: 2-s2.0-85179498220 | R70: =COUNTIF( Papers!G:G, RAW_DATA!Q70 ) = 0 -> FALSE | S70: =(COUNTIF(B:B, B70) > 1 ) -> FALSE
A71: Vasconcelos H.; Jörke M.; Grunde-Mclaughlin M.; Gerstenberg T.; Bernstein M.S.; Krishna R. | B71: Explanations Can Reduce Overreliance on AI Systems During Decision-Making | C71: 2023 | D71: Proceedings of the ACM on Human-Computer Interaction | E71: 7 | F71: CSCW1 | G71: 129 | J71: 244 | K71: 10.1145/3579605 | L71: https://www.scopus.com/pages/publications/85153706246?origin=resultslist | M71: Article | N71: Final | P71: Scopus | Q71: 2-s2.0-85153706246 | R71: =COUNTIF( Papers!G:G, RAW_DATA!Q71 ) = 0 -> FALSE | S71: =(COUNTIF(B:B, B71) > 1 ) -> FALSE
A72: Buçinca Z.; Lin P.; Gajos K.Z.; Glassman E.L. | B72: Proxy tasks and subjective measures can be misleading in evaluating explainable AI systems | C72: 2020 | D72: International Conference on Intelligent User Interfaces, Proceedings IUI | H72: 454 | I72: 464 | J72: 262 | K72: 10.1145/3377325.3377498 | L72: https://www.scopus.com/pages/publications/85082481569?origin=resultslist | M72: Conference paper | N72: Final | O72: All Open Access; Green Open Access | P72: Scopus | Q72: 2-s2.0-85082481569 | R72: =COUNTIF( Papers!G:G, RAW_DATA!Q72 ) = 0 -> FALSE | S72: =(COUNTIF(B:B, B72) > 1 ) -> FALSE
A73: Saeed W.; Omlin C. | B73: Explainable AI (XAI): A systematic meta-survey of current challenges and future opportunities | C73: 2023 | D73: Knowledge-Based Systems | E73: 263 | G73: 110273 | J73: 648 | K73: 10.1016/j.knosys.2023.110273 | L73: https://www.scopus.com/pages/publications/85146268490?origin=resultslist | M73: Article | N73: Final | O73: All Open Access; Green Open Access; Hybrid Gold Open Access | P73: Scopus | Q73: 2-s2.0-85146268490 | R73: =COUNTIF( Papers!G:G, RAW_DATA!Q73 ) = 0 -> FALSE | S73: =(COUNTIF(B:B, B73) > 1 ) -> FALSE
A74: Mariani M.M.; Perez-Vega R.; Wirtz J. | B74: AI in marketing, consumer research and psychology: A systematic literature review and research agenda | C74: 2022 | D74: Psychology and Marketing | E74: 39 | F74: 4 | H74: 755 | I74: 776 | J74: 477 | K74: 10.1002/mar.21619 | L74: https://www.scopus.com/pages/publications/85120872880?origin=resultslist | M74: Review | N74: Final | O74: All Open Access; Green Open Access; Hybrid Gold Open Access | P74: Scopus | Q74: 2-s2.0-85120872880 | R74: =COUNTIF( Papers!G:G, RAW_DATA!Q74 ) = 0 -> FALSE | S74: =(COUNTIF(B:B, B74) > 1 ) -> FALSE
A75: Lee M.K. | B75: Understanding perception of algorithmic decisions: Fairness, trust, and emotion in response to algorithmic management | C75: 2018 | D75: Big Data and Society | E75: 5 | F75: 1 | J75: 1017 | K75: 10.1177/2053951718756684 | L75: https://www.scopus.com/pages/publications/85056605201?origin=resultslist | M75: Article | N75: Final | O75: All Open Access; Gold Open Access; Green Open Access | P75: Scopus | Q75: 2-s2.0-85056605201 | R75: =COUNTIF( Papers!G:G, RAW_DATA!Q75 ) = 0 -> FALSE | S75: =(COUNTIF(B:B, B75) > 1 ) -> FALSE
A76: Gama F.; Magistretti S. | B76: Artificial intelligence in innovation management: A review of innovation capabilities and a taxonomy of AI applications | C76: 2025 | D76: Journal of Product Innovation Management | E76: 42 | F76: 1 | H76: 76 | I76: 111 | J76: 225 | K76: 10.1111/jpim.12698 | L76: https://www.scopus.com/pages/publications/85172167777?origin=resultslist | M76: Article | N76: Final | O76: All Open Access; Green Open Access | P76: Scopus | Q76: 2-s2.0-85172167777 | R76: =COUNTIF( Papers!G:G, RAW_DATA!Q76 ) = 0 -> FALSE | S76: =(COUNTIF(B:B, B76) > 1 ) -> FALSE
A77: Choudhury A.; Shamszare H. | B77: Investigating the Impact of User Trust on the Adoption and Use of ChatGPT: Survey Analysis | C77: 2023 | D77: Journal of Medical Internet Research | E77: 25 | G77: e47184 | J77: 344 | K77: 10.2196/47184 | L77: https://www.scopus.com/pages/publications/85159924829?origin=resultslist | M77: Article | N77: Final | O77: All Open Access; Gold Open Access; Green Open Access | P77: Scopus | Q77: 2-s2.0-85159924829 | R77: =COUNTIF( Papers!G:G, RAW_DATA!Q77 ) = 0 -> FALSE | S77: =(COUNTIF(B:B, B77) > 1 ) -> FALSE
A78: Aoki N. | B78: An experimental study of public trust in AI chatbots in the public sector | C78: 2020 | D78: Government Information Quarterly | E78: 37 | F78: 4 | G78: 101490 | J78: 286 | K78: 10.1016/j.giq.2020.101490 | L78: https://www.scopus.com/pages/publications/85089530712?origin=resultslist | M78: Article | N78: Final | P78: Scopus | Q78: 2-s2.0-85089530712 | R78: =COUNTIF( Papers!G:G, RAW_DATA!Q78 ) = 0 -> FALSE | S78: =(COUNTIF(B:B, B78) > 1 ) -> FALSE
A79: Buçinca Z.; Malaya M.B.; Gajos K.Z. | B79: To Trust or to Think: Cognitive Forcing Functions Can Reduce Overreliance on AI in AI-assisted Decision-making | C79: 2021 | D79: Proceedings of the ACM on Human-Computer Interaction | E79: 5 | F79: CSCW1 | G79: 188 | J79: 682 | K79: 10.1145/3449287 | L79: https://www.scopus.com/pages/publications/85115723507?origin=resultslist | M79: Article | N79: Final | O79: All Open Access; Green Open Access | P79: Scopus | Q79: 2-s2.0-85115723507 | R79: =COUNTIF( Papers!G:G, RAW_DATA!Q79 ) = 0 -> FALSE | S79: =(COUNTIF(B:B, B79) > 1 ) -> FALSE
A80: Spinner T.; Schlegel U.; Schäfer H.; El-Assady M. | B80: ExplAIner: A Visual Analytics Framework for Interactive and Explainable Machine Learning | C80: 2020 | D80: IEEE Transactions on Visualization and Computer Graphics | E80: 26 | F80: 1 | G80: 8807299 | H80: 1064 | I80: 1074 | J80: 246 | K80: 10.1109/TVCG.2019.2934629 | L80: https://www.scopus.com/pages/publications/85075593782?origin=resultslist | M80: Article | N80: Final | O80: All Open Access; Green Open Access | P80: Scopus | Q80: 2-s2.0-85075593782 | R80: =COUNTIF( Papers!G:G, RAW_DATA!Q80 ) = 0 -> FALSE | S80: =(COUNTIF(B:B, B80) > 1 ) -> FALSE
A81: Rudolph C.W.; Allan B.; Clark M.; Hertel G.; Hirschi A.; Kunze F.; Shockley K.; Shoss M.; Sonnentag S.; Zacher H. | B81: Pandemics: Implications for research and practice in industrial and organizational psychology | C81: 2021 | D81: Industrial and Organizational Psychology | E81: 14 | F81: 46024 | H81: 1 | I81: 35 | J81: 368 | K81: 10.1017/iop.2020.48 | L81: https://www.scopus.com/pages/publications/85106604957?origin=resultslist | M81: Article | N81: Final | O81: All Open Access; Green Open Access | P81: Scopus | Q81: 2-s2.0-85106604957 | R81: =COUNTIF( Papers!G:G, RAW_DATA!Q81 ) = 0 -> FALSE | S81: =(COUNTIF(B:B, B81) > 1 ) -> FALSE
A82: Lai V.; Tan C. | B82: On human predictions with explanations and predictions of machine learning models: A case study on deception detection | C82: 2019 | D82: FAT* 2019 - Proceedings of the 2019 Conference on Fairness, Accountability, and Transparency | H82: 29 | I82: 38 | J82: 341 | K82: 10.1145/3287560.3287590 | L82: https://www.scopus.com/pages/publications/85061781028?origin=resultslist | M82: Conference paper | N82: Final | O82: All Open Access; Green Open Access | P82: Scopus | Q82: 2-s2.0-85061781028 | R82: =COUNTIF( Papers!G:G, RAW_DATA!Q82 ) = 0 -> FALSE | S82: =(COUNTIF(B:B, B82) > 1 ) -> FALSE
A83: Schepman A.; Rodway P. | B83: Initial validation of the general attitudes towards Artificial Intelligence Scale | C83: 2020 | D83: Computers in Human Behavior Reports | E83: 1 | G83: 100014 | J83: 476 | K83: 10.1016/j.chbr.2020.100014 | L83: https://www.scopus.com/pages/publications/85096303826?origin=resultslist | M83: Article | N83: Final | O83: All Open Access; Gold Open Access; Green Open Access | P83: Scopus | Q83: 2-s2.0-85096303826 | R83: =COUNTIF( Papers!G:G, RAW_DATA!Q83 ) = 0 -> FALSE | S83: =(COUNTIF(B:B, B83) > 1 ) -> FALSE
A84: de Visser E.J.; Pak R.; Shaw T.H. | B84: From ‘automation’ to ‘autonomy’: the importance of trust repair in human–machine interaction | C84: 2018 | D84: Ergonomics | E84: 61 | F84: 10 | H84: 1409 | I84: 1427 | J84: 329 | K84: 10.1080/00140139.2018.1457725 | L84: https://www.scopus.com/pages/publications/85045104296?origin=resultslist | M84: Article | N84: Final | P84: Scopus | Q84: 2-s2.0-85045104296 | R84: =COUNTIF( Papers!G:G, RAW_DATA!Q84 ) = 0 -> FALSE | S84: =(COUNTIF(B:B, B84) > 1 ) -> FALSE
A85: Kaplan A.D.; Kessler T.T.; Brill J.C.; Hancock P.A. | B85: Trust in Artificial Intelligence: Meta-Analytic Findings | C85: 2023 | D85: Human Factors | E85: 65 | F85: 2 | H85: 337 | I85: 359 | J85: 291 | K85: 10.1177/00187208211013988 | L85: https://www.scopus.com/pages/publications/85106720283?origin=resultslist | M85: Article | N85: Final | O85: All Open Access; Bronze Open Access | P85: Scopus | Q85: 2-s2.0-85106720283 | R85: =COUNTIF( Papers!G:G, RAW_DATA!Q85 ) = 0 -> FALSE | S85: =(COUNTIF(B:B, B85) > 1 ) -> FALSE
A86: Kim N.J.; Kim M.K. | B86: Teacher’s Perceptions of Using an Artificial Intelligence-Based Educational Tool for Scientific Writing | C86: 2022 | D86: Frontiers in Education | E86: 7 | G86: 755914 | J86: 221 | K86: 10.3389/feduc.2022.755914 | L86: https://www.scopus.com/pages/publications/85128424819?origin=resultslist | M86: Article | N86: Final | O86: All Open Access; Gold Open Access; Green Open Access | P86: Scopus | Q86: 2-s2.0-85128424819 | R86: =COUNTIF( Papers!G:G, RAW_DATA!Q86 ) = 0 -> FALSE | S86: =(COUNTIF(B:B, B86) > 1 ) -> FALSE
A87: Körber M.; Baseler E.; Bengler K. | B87: Introduction matters: Manipulating trust in automation and reliance in automated driving | C87: 2018 | D87: Applied Ergonomics | E87: 66 | H87: 18 | I87: 31 | J87: 355 | K87: 10.1016/j.apergo.2017.07.006 | L87: https://www.scopus.com/pages/publications/85029816073?origin=resultslist | M87: Article | N87: Final | P87: Scopus | Q87: 2-s2.0-85029816073 | R87: =COUNTIF( Papers!G:G, RAW_DATA!Q87 ) = 0 -> FALSE | S87: =(COUNTIF(B:B, B87) > 1 ) -> FALSE
A88: Celik I. | B88: Towards Intelligent-TPACK: An empirical study on teachers’ professional knowledge to ethically integrate artificial intelligence (AI)-based tools into education | C88: 2023 | D88: Computers in Human Behavior | E88: 138 | G88: 107468 | J88: 624 | K88: 10.1016/j.chb.2022.107468 | L88: https://www.scopus.com/pages/publications/85137060930?origin=resultslist | M88: Article | N88: Final | O88: All Open Access; Green Open Access; Hybrid Gold Open Access | P88: Scopus | Q88: 2-s2.0-85137060930 | R88: =COUNTIF( Papers!G:G, RAW_DATA!Q88 ) = 0 -> FALSE | S88: =(COUNTIF(B:B, B88) > 1 ) -> FALSE
A89: Lebovitz S.; Lifshitz-Assaf H.; Levina N. | B89: To Engage or Not to Engage with AI for Critical Judgments: How Professionals Deal with Opacity When Using AI for Medical Diagnosis | C89: 2022 | D89: Organization Science | E89: 33 | F89: 1 | H89: 126 | I89: 148 | J89: 406 | K89: 10.1287/ORSC.2021.1549 | L89: https://www.scopus.com/pages/publications/85125569707?origin=resultslist | M89: Review | N89: Final | P89: Scopus | Q89: 2-s2.0-85125569707 | R89: =COUNTIF( Papers!G:G, RAW_DATA!Q89 ) = 0 -> FALSE | S89: =(COUNTIF(B:B, B89) > 1 ) -> FALSE
A90: Jiang Z.; Araki J.; Ding H.; Neubig G. | B90: How can we know when language models know? On the calibration of language models for question answering | C90: 2021 | D90: Transactions of the Association for Computational Linguistics | E90: 9 | H90: 962 | I90: 977 | J90: 326 | K90: 10.1162/tacl_a_00407 | L90: https://www.scopus.com/pages/publications/85119501865?origin=resultslist | M90: Article | N90: Final | O90: All Open Access; Gold Open Access; Green Open Access | P90: Scopus | Q90: 2-s2.0-85119501865 | R90: =COUNTIF( Papers!G:G, RAW_DATA!Q90 ) = 0 -> FALSE | S90: =(COUNTIF(B:B, B90) > 1 ) -> FALSE
A91: Makarius E.E.; Mukherjee D.; Fox J.D.; Fox A.K. | B91: Rising with the machines: A sociotechnical framework for bringing artificial intelligence into the organization | C91: 2020 | D91: Journal of Business Research | E91: 120 | H91: 262 | I91: 273 | J91: 577 | K91: 10.1016/j.jbusres.2020.07.045 | L91: https://www.scopus.com/pages/publications/85089816705?origin=resultslist | M91: Article | N91: Final | O91: All Open Access; Hybrid Gold Open Access | P91: Scopus | Q91: 2-s2.0-85089816705 | R91: =COUNTIF( Papers!G:G, RAW_DATA!Q91 ) = 0 -> FALSE | S91: =(COUNTIF(B:B, B91) > 1 ) -> FALSE
A92: Larson L.; DeChurch L.A. | B92: Leading teams in the digital age: Four perspectives on technology and what they mean for leading teams | C92: 2020 | D92: Leadership Quarterly | E92: 31 | F92: 1 | G92: 101377 | J92: 278 | K92: 10.1016/j.leaqua.2019.101377 | L92: https://www.scopus.com/pages/publications/85077758620?origin=resultslist | M92: Article | N92: Final | O92: All Open Access; Green Open Access | P92: Scopus | Q92: 2-s2.0-85077758620 | R92: =COUNTIF( Papers!G:G, RAW_DATA!Q92 ) = 0 -> FALSE | S92: =(COUNTIF(B:B, B92) > 1 ) -> FALSE
A93: Kelly S.; Kaye S.-A.; Oviedo-Trespalacios O. | B93: What factors contribute to the acceptance of artificial intelligence? A systematic review | C93: 2023 | D93: Telematics and Informatics | E93: 77 | G93: 101925 | J93: 756 | K93: 10.1016/j.tele.2022.101925 | L93: https://www.scopus.com/pages/publications/85144829011?origin=resultslist | M93: Article | N93: Final | O93: All Open Access; Green Open Access; Hybrid Gold Open Access | P93: Scopus | Q93: 2-s2.0-85144829011 | R93: =COUNTIF( Papers!G:G, RAW_DATA!Q93 ) = 0 -> FALSE | S93: =(COUNTIF(B:B, B93) > 1 ) -> FALSE
A94: Wang X.; Yin M. | B94: Are Explanations Helpful? A Comparative Study of the Effects of Explanations in AI-Assisted Decision-Making | C94: 2021 | D94: International Conference on Intelligent User Interfaces, Proceedings IUI | H94: 318 | I94: 328 | J94: 301 | K94: 10.1145/3397481.3450650 | L94: https://www.scopus.com/pages/publications/85104503567?origin=resultslist | M94: Conference paper | N94: Final | O94: All Open Access; Gold Open Access | P94: Scopus | Q94: 2-s2.0-85104503567 | R94: =COUNTIF( Papers!G:G, RAW_DATA!Q94 ) = 0 -> FALSE | S94: =(COUNTIF(B:B, B94) > 1 ) -> FALSE
A95: Bansal G.; Nushi B.; Kamar E.; Weld D.S.; Lasecki W.S.; Horvitz E. | B95: Updates in human-ai teams: Understanding and addressing the performance/compatibility tradeoff | C95: 2019 | D95: 33rd AAAI Conference on Artificial Intelligence, AAAI 2019, 31st Innovative Applications of Artificial Intelligence Conference, IAAI 2019 and the 9th AAAI Symposium on Educational Advances in Artificial Intelligence, EAAI 2019 | H95: 2429 | I95: 2437 | J95: 266 | K95: 10.1609/aaai.v33i01.33012429 | L95: https://www.scopus.com/pages/publications/85079599165?origin=resultslist | M95: Conference paper | N95: Final | O95: All Open Access; Gold Open Access | P95: Scopus | Q95: 2-s2.0-85079599165 | R95: =COUNTIF( Papers!G:G, RAW_DATA!Q95 ) = 0 -> FALSE | S95: =(COUNTIF(B:B, B95) > 1 ) -> FALSE
A96: Rheu M.; Shin J.Y.; Peng W.; Huh-Yoo J. | B96: Systematic Review: Trust-Building Factors and Implications for Conversational Agent Design | C96: 2021 | D96: International Journal of Human-Computer Interaction | E96: 37 | F96: 1 | H96: 81 | I96: 96 | J96: 291 | K96: 10.1080/10447318.2020.1807710 | L96: https://www.scopus.com/pages/publications/85090125043?origin=resultslist | M96: Article | N96: Final | O96: All Open Access; Green Open Access | P96: Scopus | Q96: 2-s2.0-85090125043 | R96: =COUNTIF( Papers!G:G, RAW_DATA!Q96 ) = 0 -> FALSE | S96: =(COUNTIF(B:B, B96) > 1 ) -> FALSE
A97: Vaccaro M.; Almaatouq A.; Malone T. | B97: When combinations of humans and AI are useful: A systematic review and meta-analysis | C97: 2024 | D97: Nature Human Behaviour | E97: 8 | F97: 12 | H97: 2293 | I97: 2303 | J97: 237 | K97: 10.1038/s41562-024-02024-1 | L97: https://www.scopus.com/pages/publications/85207410244?origin=resultslist | M97: Article | N97: Final | O97: All Open Access; Green Open Access; Hybrid Gold Open Access | P97: Scopus | Q97: 2-s2.0-85207410244 | R97: =COUNTIF( Papers!G:G, RAW_DATA!Q97 ) = 0 -> FALSE | S97: =(COUNTIF(B:B, B97) > 1 ) -> FALSE
A98: Chiu T.K.F.; Xia Q.; Zhou X.; Chai C.S.; Cheng M. | B98: Systematic literature review on opportunities, challenges, and future research recommendations of artificial intelligence in education | C98: 2023 | D98: Computers and Education: Artificial Intelligence | E98: 4 | G98: 100118 | J98: 810 | K98: 10.1016/j.caeai.2022.100118 | L98: https://www.scopus.com/pages/publications/85144966908?origin=resultslist | M98: Review | N98: Final | O98: All Open Access; Gold Open Access; Green Open Access | P98: Scopus | Q98: 2-s2.0-85144966908 | R98: =COUNTIF( Papers!G:G, RAW_DATA!Q98 ) = 0 -> FALSE | S98: =(COUNTIF(B:B, B98) > 1 ) -> FALSE
A99: Sacha D.; Senaratne H.; Kwon B.C.; Ellis G.; Keim D.A. | B99: The Role of Uncertainty, Awareness, and Trust in Visual Analytics | C99: 2016 | D99: IEEE Transactions on Visualization and Computer Graphics | E99: 22 | F99: 1 | G99: 7192716 | H99: 240 | I99: 249 | J99: 236 | K99: 10.1109/TVCG.2015.2467591 | L99: https://www.scopus.com/pages/publications/84946595461?origin=resultslist | M99: Article | N99: Final | O99: All Open Access; Green Open Access | P99: Scopus | Q99: 2-s2.0-84946595461 | R99: =COUNTIF( Papers!G:G, RAW_DATA!Q99 ) = 0 -> FALSE | S99: =(COUNTIF(B:B, B99) > 1 ) -> FALSE
A100: Choi S.; Jang Y.; Kim H. | B100: Influence of Pedagogical Beliefs and Perceived Trust on Teachers’ Acceptance of Educational Artificial Intelligence Tools | C100: 2023 | D100: International Journal of Human-Computer Interaction | E100: 39 | F100: 4 | H100: 910 | I100: 922 | J100: 222 | K100: 10.1080/10447318.2022.2049145 | L100: https://www.scopus.com/pages/publications/85129236620?origin=resultslist | M100: Article | N100: Final | P100: Scopus | Q100: 2-s2.0-85129236620 | R100: =COUNTIF( Papers!G:G, RAW_DATA!Q100 ) = 0 -> FALSE | S100: =(COUNTIF(B:B, B100) > 1 ) -> FALSE
...

Sheet Papers
A1: Reference | B1: Authors | C1: Title | D1: Type | E1: Title Screening | F1: Abstract Screening | G1: EID | H1: [Autofilled] DUPLICATE EID | I1: [Autofilled] DUPLICATE TITLE
B2: Stepin I.; Alonso J.M.; Catala A.; Pereira-Farina M. | C2: A Survey of Contrastive and Counterfactual Explanation Generation Methods for Explainable Artificial Intelligence | D2: N/A | E2: Yes | F2: No | G2: =_xlfn.XLOOKUP( C2,RAW_DATA!B:B, RAW_DATA!Q:Q, "NOT FOUND" ) -> 2-s2.0-85099601493 | H2: =COUNTIF( G:G, G2 ) > 1 -> FALSE | I2: =COUNTIF( C:C, C2 ) > 1 -> FALSE
A3: nazar_hci_xai_healthcare | B3: Nazar M.; Alam M.M.; Yafi E.; Su'Ud M.M. | C3: A Systematic Review of Human-Computer Interaction and Explainable Artificial Intelligence in Healthcare with Artificial Intelligence Techniques | D3: Theoretical | E3: Yes | F3: Yes | G3: =_xlfn.XLOOKUP( C3,RAW_DATA!B:B, RAW_DATA!Q:Q, "NOT FOUND" ) -> 2-s2.0-85119430656 | H3: =COUNTIF( G:G, G3 ) > 1 -> FALSE | I3: =COUNTIF( C:C, C3 ) > 1 -> FALSE
A4: young_patient_systematic_review | B4: Young A.T.; Amara D.; Bhattacharya A.; Wei M.L. | C4: Patient and general public attitudes towards clinical artificial intelligence: a mixed methods systematic review | D4: Theoretical | E4: Yes | F4: Yes | G4: =_xlfn.XLOOKUP( C4,RAW_DATA!B:B, RAW_DATA!Q:Q, "NOT FOUND" ) -> 2-s2.0-85115041953 | H4: =COUNTIF( G:G, G4 ) > 1 -> FALSE | I4: =COUNTIF( C:C, C4 ) > 1 -> FALSE
B5: Rashid A.B.; Kausik M.A.K. | C5: AI revolutionizing industries worldwide: A comprehensive overview of its diverse applications | D5: N/A | E5: Yes | F5: No | G5: =_xlfn.XLOOKUP( C5,RAW_DATA!B:B, RAW_DATA!Q:Q, "NOT FOUND" ) -> 2-s2.0-85204730281 | H5: =COUNTIF( G:G, G5 ) > 1 -> FALSE | I5: =COUNTIF( C:C, C5 ) > 1 -> FALSE
A6: Tong_artificial_intelligence_feedback | B6: Tong S.; Jia N.; Luo X.; Fang Z. | C6: The Janus face of artificial intelligence feedback: Deployment versus disclosure effects on employee performance | D6: Theoretical | E6: Yes | F6: Yes | G6: =_xlfn.XLOOKUP( C6,RAW_DATA!B:B, RAW_DATA!Q:Q, "NOT FOUND" ) -> 2-s2.0-85109705359 | H6: =COUNTIF( G:G, G6 ) > 1 -> FALSE | I6: =COUNTIF( C:C, C6 ) > 1 -> FALSE
A7: zhang_automated_vehicle_acceptance | B7: Zhang T.; Tao D.; Qu X.; Zhang X.; Zeng J.; Zhu H.; Zhu H. | C7: Automated vehicle acceptance in China: Social influence and initial trust are key determinants | D7: Empirical | E7: Yes | F7: Yes | G7: =_xlfn.XLOOKUP( C7,RAW_DATA!B:B, RAW_DATA!Q:Q, "NOT FOUND" ) -> 2-s2.0-85078934939 | H7: =COUNTIF( G:G, G7 ) > 1 -> FALSE | I7: =COUNTIF( C:C, C7 ) > 1 -> FALSE
A8: tussyadiah_do_travelers_trust | B8: Tussyadiah I.P.; Zach F.J.; Wang J. | C8: Do travelers trust intelligent service robots? | D8: Practical | E8: Yes | F8: Yes | G8: =_xlfn.XLOOKUP( C8,RAW_DATA!B:B, RAW_DATA!Q:Q, "NOT FOUND" ) -> 2-s2.0-85079861440 | H8: =COUNTIF( G:G, G8 ) > 1 -> FALSE | I8: =COUNTIF( C:C, C8 ) > 1 -> FALSE
B9: Rudin C.; Chen C.; Chen Z.; Huang H.; Semenova L.; Zhong C. | C9: Interpretable machine learning: Fundamental principles and 10 grand challenges | E9: No | F9: No | G9: =_xlfn.XLOOKUP( C9,RAW_DATA!B:B, RAW_DATA!Q:Q, "NOT FOUND" ) -> 2-s2.0-85125573696 | H9: =COUNTIF( G:G, G9 ) > 1 -> FALSE | I9: =COUNTIF( C:C, C9 ) > 1 -> FALSE
A10: choudhury_asan_2020_trust_clinicians | B10: Asan O.; Bayrak A.E.; Choudhury A. | C10: Artificial Intelligence and Human Trust in Healthcare: Focus on Clinicians | D10: Theoretical | E10: Yes | F10: Yes | G10: =_xlfn.XLOOKUP( C10,RAW_DATA!B:B, RAW_DATA!Q:Q, "NOT FOUND" ) -> 2-s2.0-85086727009 | H10: =COUNTIF( G:G, G10 ) > 1 -> FALSE | I10: =COUNTIF( C:C, C10 ) > 1 -> FALSE
B11: Hergeth S.; Lorenz L.; Vilimek R.; Krems J.F. | C11: Keep Your Scanners Peeled: Gaze Behavior as a Measure of Automation Trust during Highly Automated Driving | D11: N/A | E11: Yes | F11: No | G11: =_xlfn.XLOOKUP( C11,RAW_DATA!B:B, RAW_DATA!Q:Q, "NOT FOUND" ) -> 2-s2.0-84962910809 | H11: =COUNTIF( G:G, G11 ) > 1 -> FALSE | I11: =COUNTIF( C:C, C11 ) > 1 -> FALSE
B12: Honig S.; Oron-Gilad T. | C12: Understanding and resolving failures in human-robot interaction: Literature review and model development | E12: No | F12: No | G12: =_xlfn.XLOOKUP( C12,RAW_DATA!B:B, RAW_DATA!Q:Q, "NOT FOUND" ) -> 2-s2.0-85048531596 | H12: =COUNTIF( G:G, G12 ) > 1 -> FALSE | I12: =COUNTIF( C:C, C12 ) > 1 -> FALSE
A13: carsten_hmi_automated_cars | B13: Carsten O.; Martens M.H. | C13: How can humans understand their automated cars? HMI principles, problems and solutions | D13: Theoretical | E13: Yes | F13: Yes | G13: =_xlfn.XLOOKUP( C13,RAW_DATA!B:B, RAW_DATA!Q:Q, "NOT FOUND" ) -> 2-s2.0-85046726952 | H13: =COUNTIF( G:G, G13 ) > 1 -> FALSE | I13: =COUNTIF( C:C, C13 ) > 1 -> FALSE
A14: vilone_longo_2021 | B14: Vilone G.; Longo L. | C14: Notions of explainability and evaluation approaches for explainable artificial intelligence | D14: Theoretical | E14: Yes | F14: Yes | G14: =_xlfn.XLOOKUP( C14,RAW_DATA!B:B, RAW_DATA!Q:Q, "NOT FOUND" ) -> 2-s2.0-85107637272 | H14: =COUNTIF( G:G, G14 ) > 1 -> FALSE | I14: =COUNTIF( C:C, C14 ) > 1 -> FALSE
B15: Pereira V.; Hadjielias E.; Christofi M.; Vrontis D. | C15: A systematic literature review on the impact of artificial intelligence on workplace outcomes: A multi-process perspective | E15: No | F15: No | G15: =_xlfn.XLOOKUP( C15,RAW_DATA!B:B, RAW_DATA!Q:Q, "NOT FOUND" ) -> 2-s2.0-85114687655 | H15: =COUNTIF( G:G, G15 ) > 1 -> FALSE | I15: =COUNTIF( C:C, C15 ) > 1 -> FALSE
B16: Langer M.; Oster D.; Speith T.; Hermanns H.; Kästner L.; Schmidt E.; Sesing A.; Baum K. | C16: What do we want from Explainable Artificial Intelligence (XAI)? – A stakeholder perspective on XAI and a conceptual model guiding interdisciplinary XAI research | E16: No | F16: No | G16: =_xlfn.XLOOKUP( C16,RAW_DATA!B:B, RAW_DATA!Q:Q, "NOT FOUND" ) -> 2-s2.0-85101531468 | H16: =COUNTIF( G:G, G16 ) > 1 -> FALSE | I16: =COUNTIF( C:C, C16 ) > 1 -> FALSE
B17: Chalmers D.; MacKenzie N.G.; Carter S. | C17: Artificial Intelligence and Entrepreneurship: Implications for Venture Creation in the Fourth Industrial Revolution | E17: Yes | F17: No | G17: =_xlfn.XLOOKUP( C17,RAW_DATA!B:B, RAW_DATA!Q:Q, "NOT FOUND" ) -> 2-s2.0-85087930775 | H17: =COUNTIF( G:G, G17 ) > 1 -> FALSE | I17: =COUNTIF( C:C, C17 ) > 1 -> FALSE
B18: Chowdhury S.; Budhwar P.; Dey P.K.; Joel-Edgar S.; Abadie A. | C18: AI-employee collaboration and business performance: Integrating knowledge-based view, socio-technical systems and organisational socialisation framework | E18: No | F18: No | G18: =_xlfn.XLOOKUP( C18,RAW_DATA!B:B, RAW_DATA!Q:Q, "NOT FOUND" ) -> 2-s2.0-85124046364 | H18: =COUNTIF( G:G, G18 ) > 1 -> FALSE | I18: =COUNTIF( C:C, C18 ) > 1 -> FALSE
B19: Dellermann D.; Ebel P.; Söllner M.; Leimeister J.M. | C19: Hybrid Intelligence | E19: No | F19: No | G19: =_xlfn.XLOOKUP( C19,RAW_DATA!B:B, RAW_DATA!Q:Q, "NOT FOUND" ) -> 2-s2.0-85069455009 | H19: =COUNTIF( G:G, G19 ) > 1 -> FALSE | I19: =COUNTIF( C:C, C19 ) > 1 -> FALSE
B20: Man Tang P.; Koopman J.; McClean S.T.; Zhang J.H.; Hon Li C.; de Cremer D.; Lu Y.; Stewart Ng C.T. | C20: WHEN CONSCIENTIOUS EMPLOYEES MEET INTELLIGENT MACHINES: AN INTEGRATIVE APPROACH INSPIRED BY COMPLEMENTARITY THEORY AND ROLE THEORY | E20: No | F20: No | G20: =_xlfn.XLOOKUP( C20,RAW_DATA!B:B, RAW_DATA!Q:Q, "NOT FOUND" ) -> 2-s2.0-85135124659 | H20: =COUNTIF( G:G, G20 ) > 1 -> FALSE | I20: =COUNTIF( C:C, C20 ) > 1 -> FALSE
B21: Mirbabaie M.; Brünker F.; Möllmann Frick N.R.J.; Stieglitz S. | C21: The rise of artificial intelligence – understanding the AI identity threat at the workplace | E21: No | F21: No | G21: =_xlfn.XLOOKUP( C21,RAW_DATA!B:B, RAW_DATA!Q:Q, "NOT FOUND" ) -> 2-s2.0-85116415765 | H21: =COUNTIF( G:G, G21 ) > 1 -> FALSE | I21: =COUNTIF( C:C, C21 ) > 1 -> FALSE
B22: Bedué P.; Fritzsche A. | C22: Can we trust AI? An empirical investigation of trust requirements and guide to successful AI adoption | E22: No | F22: No | G22: =_xlfn.XLOOKUP( C22,RAW_DATA!B:B, RAW_DATA!Q:Q, "NOT FOUND" ) -> 2-s2.0-85106282628 | H22: =COUNTIF( G:G, G22 ) > 1 -> FALSE | I22: =COUNTIF( C:C, C22 ) > 1 -> FALSE
B23: Parent-Rocheleau X.; Parker S.K. | C23: Algorithms as work designers: How algorithmic management influences the design of jobs | E23: No | F23: No | G23: =_xlfn.XLOOKUP( C23,RAW_DATA!B:B, RAW_DATA!Q:Q, "NOT FOUND" ) -> 2-s2.0-85105550128 | H23: =COUNTIF( G:G, G23 ) > 1 -> FALSE | I23: =COUNTIF( C:C, C23 ) > 1 -> FALSE
B24: Hayes B.; Shah J.A. | C24: Improving Robot Controller Transparency Through Autonomous Policy Explanation | E24: No | F24: No | G24: =_xlfn.XLOOKUP( C24,RAW_DATA!B:B, RAW_DATA!Q:Q, "NOT FOUND" ) -> 2-s2.0-85021787797 | H24: =COUNTIF( G:G, G24 ) > 1 -> FALSE | I24: =COUNTIF( C:C, C24 ) > 1 -> FALSE
A25: hayes2017improving | B25: Dudley J.J.; Kristensson P.O. | C25: A review of user interface design for interactive machine learning | D25: Empirical | E25: Yes | F25: Yes | G25: =_xlfn.XLOOKUP( C25,RAW_DATA!B:B, RAW_DATA!Q:Q, "NOT FOUND" ) -> 2-s2.0-85058625902 | H25: =COUNTIF( G:G, G25 ) > 1 -> FALSE | I25: =COUNTIF( C:C, C25 ) > 1 -> FALSE
B26: Chowdhury S.; Dey P.; Joel-Edgar S.; Bhattacharya S.; Rodriguez-Espindola O.; Abadie A.; Truong L. | C26: Unlocking the value of artificial intelligence in human resource management through AI capability framework | E26: No | F26: No | G26: =_xlfn.XLOOKUP( C26,RAW_DATA!B:B, RAW_DATA!Q:Q, "NOT FOUND" ) -> 2-s2.0-85127325455 | H26: =COUNTIF( G:G, G26 ) > 1 -> FALSE | I26: =COUNTIF( C:C, C26 ) > 1 -> FALSE
B27: Chiou E.K.; Lee J.D. | C27: Trusting Automation: Designing for Responsivity and Resilience | E27: No | F27: No | G27: =_xlfn.XLOOKUP( C27,RAW_DATA!B:B, RAW_DATA!Q:Q, "NOT FOUND" ) -> 2-s2.0-85104981249 | H27: =COUNTIF( G:G, G27 ) > 1 -> FALSE | I27: =COUNTIF( C:C, C27 ) > 1 -> FALSE
B28: Liu K.; Tao D. | C28: The roles of trust, personalization, loss of privacy, and anthropomorphism in public acceptance of smart healthcare services | E28: No | F28: No | G28: =_xlfn.XLOOKUP( C28,RAW_DATA!B:B, RAW_DATA!Q:Q, "NOT FOUND" ) -> 2-s2.0-85115048327 | H28: =COUNTIF( G:G, G28 ) > 1 -> FALSE | I28: =COUNTIF( C:C, C28 ) > 1 -> FALSE
A29: chiou_trusting_automation | B29: Yam K.C.; Tang P.M.; Jackson J.C.; Su R.; Gray K. | C29: The Rise of Robots Increases Job Insecurity and Maladaptive Workplace Behaviors: Multimethod Evidence | D29: Theoretical | E29: Yes | F29: Yes | G29: =_xlfn.XLOOKUP( C29,RAW_DATA!B:B, RAW_DATA!Q:Q, "NOT FOUND" ) -> 2-s2.0-85140762473 | H29: =COUNTIF( G:G, G29 ) > 1 -> FALSE | I29: =COUNTIF( C:C, C29 ) > 1 -> FALSE
B30: Kohn S.C.; de Visser E.J.; Wiese E.; Lee Y.-C.; Shaw T.H. | C30: Measurement of Trust in Automation: A Narrative Review and Reference Guide | E30: Yes | F30: No | G30: =_xlfn.XLOOKUP( C30,RAW_DATA!B:B, RAW_DATA!Q:Q, "NOT FOUND" ) -> 2-s2.0-85118576621 | H30: =COUNTIF( G:G, G30 ) > 1 -> FALSE | I30: =COUNTIF( C:C, C30 ) > 1 -> FALSE
B31: Hengstler M.; Enkel E.; Duelli S. | C31: Applied artificial intelligence and trust-The case of autonomous vehicles and medical assistance devices | E31: No | F31: No | G31: =_xlfn.XLOOKUP( C31,RAW_DATA!B:B, RAW_DATA!Q:Q, "NOT FOUND" ) -> 2-s2.0-84957895151 | H31: =COUNTIF( G:G, G31 ) > 1 -> FALSE | I31: =COUNTIF( C:C, C31 ) > 1 -> FALSE
A32: john_measurement_of_trust | B32: Bach T.A.; Khan A.; Hallock H.; Beltrão G.; Sousa S. | C32: A Systematic Literature Review of User Trust in AI-Enabled Systems: An HCI Perspective | D32: Theoretical | E32: Yes | F32: Yes | G32: =_xlfn.XLOOKUP( C32,RAW_DATA!B:B, RAW_DATA!Q:Q, "NOT FOUND" ) -> 2-s2.0-85141953140 | H32: =COUNTIF( G:G, G32 ) > 1 -> FALSE | I32: =COUNTIF( C:C, C32 ) > 1 -> FALSE
B33: Sun W.; Bocchini P.; Davison B.D. | C33: Applications of artificial intelligence for disaster management | E33: Yes | F33: No | G33: =_xlfn.XLOOKUP( C33,RAW_DATA!B:B, RAW_DATA!Q:Q, "NOT FOUND" ) -> 2-s2.0-85087516664 | H33: =COUNTIF( G:G, G33 ) > 1 -> FALSE | I33: =COUNTIF( C:C, C33 ) > 1 -> FALSE
B34: Glikson E.; Woolley A.W. | C34: Human trust in artificial intelligence: Review of empirical research | E34: Yes | F34: No | G34: =_xlfn.XLOOKUP( C34,RAW_DATA!B:B, RAW_DATA!Q:Q, "NOT FOUND" ) -> 2-s2.0-85087295894 | H34: =COUNTIF( G:G, G34 ) > 1 -> FALSE | I34: =COUNTIF( C:C, C34 ) > 1 -> FALSE
A35: bach_systematic_literature_review | B35: Xu Z.; Zhang K.; Min H.; Wang Z.; Zhao X.; Liu P. | C35: What drives people to accept automated vehicles? Findings from a field experiment | D35: Empirical | E35: Yes | F35: Yes | G35: =_xlfn.XLOOKUP( C35,RAW_DATA!B:B, RAW_DATA!Q:Q, "NOT FOUND" ) -> 2-s2.0-85050653532 | H35: =COUNTIF( G:G, G35 ) > 1 -> FALSE | I35: =COUNTIF( C:C, C35 ) > 1 -> FALSE
B36: Haleem A.; Javaid M.; Asim Qadri M.; Pratap Singh R.; Suman R. | C36: Artificial intelligence (AI) applications for marketing: A literature-based study | E36: No | F36: No | G36: =_xlfn.XLOOKUP( C36,RAW_DATA!B:B, RAW_DATA!Q:Q, "NOT FOUND" ) -> 2-s2.0-85137403442 | H36: =COUNTIF( G:G, G36 ) > 1 -> FALSE | I36: =COUNTIF( C:C, C36 ) > 1 -> FALSE
A37: glickson_2020_review_of_empirical_research | B37: Mathur M.B.; Reichling D.B. | C37: Navigating a social world with robot partners: A quantitative cartography of the Uncanny Valley | D37: Theoretical | E37: Yes | F37: Yes | G37: =_xlfn.XLOOKUP( C37,RAW_DATA!B:B, RAW_DATA!Q:Q, "NOT FOUND" ) -> 2-s2.0-84942154696 | H37: =COUNTIF( G:G, G37 ) > 1 -> FALSE | I37: =COUNTIF( C:C, C37 ) > 1 -> FALSE
B38: Abdul A.; Vermeulen J.; Wang D.; Lim B.Y.; Kankanhalli M. | C38: Trends and trajectories for explainable, accountable and intelligible systems: An HCI research agenda | E38: Yes | F38: No | G38: =_xlfn.XLOOKUP( C38,RAW_DATA!B:B, RAW_DATA!Q:Q, "NOT FOUND" ) -> 2-s2.0-85044532871 | H38: =COUNTIF( G:G, G38 ) > 1 -> FALSE | I38: =COUNTIF( C:C, C38 ) > 1 -> FALSE
B39: Zhang Y.; Xiong F.; Xie Y.; Fan X.; Gu H. | C39: The Impact of Artificial Intelligence and Blockchain on the Accounting Profession | E39: No | F39: No | G39: =_xlfn.XLOOKUP( C39,RAW_DATA!B:B, RAW_DATA!Q:Q, "NOT FOUND" ) -> 2-s2.0-85087542875 | H39: =COUNTIF( G:G, G39 ) > 1 -> FALSE | I39: =COUNTIF( C:C, C39 ) > 1 -> FALSE
B40: Nastjuk I.; Herrenkind B.; Marrone M.; Brendel A.B.; Kolbe L.M. | C40: What drives the acceptance of autonomous driving? An investigation of acceptance factors from an end-user's perspective | E40: No | F40: No | G40: =_xlfn.XLOOKUP( C40,RAW_DATA!B:B, RAW_DATA!Q:Q, "NOT FOUND" ) -> 2-s2.0-85091505828 | H40: =COUNTIF( G:G, G40 ) > 1 -> FALSE | I40: =COUNTIF( C:C, C40 ) > 1 -> FALSE
B41: Kuziemski M.; Misuraca G. | C41: AI governance in the public sector: Three tales from the frontiers of automated decision-making in democratic settings | E41: No | F41: No | G41: =_xlfn.XLOOKUP( C41,RAW_DATA!B:B, RAW_DATA!Q:Q, "NOT FOUND" ) -> 2-s2.0-85084122224 | H41: =COUNTIF( G:G, G41 ) > 1 -> FALSE | I41: =COUNTIF( C:C, C41 ) > 1 -> FALSE
B42: Ruff L.; Kauffmann J.R.; Vandermeulen R.A.; Montavon G.; Samek W.; Kloft M.; Dietterich T.G.; Muller K.-R. | C42: A Unifying Review of Deep and Shallow Anomaly Detection | E42: No | F42: No | G42: =_xlfn.XLOOKUP( C42,RAW_DATA!B:B, RAW_DATA!Q:Q, "NOT FOUND" ) -> 2-s2.0-85100863824 | H42: =COUNTIF( G:G, G42 ) > 1 -> FALSE | I42: =COUNTIF( C:C, C42 ) > 1 -> FALSE
B43: Haefner N.; Wincent J.; Parida V.; Gassmann O. | C43: Artificial intelligence and innovation management: A review, framework, and research agenda✰ | E43: Yes | F43: No | G43: =_xlfn.XLOOKUP( C43,RAW_DATA!B:B, RAW_DATA!Q:Q, "NOT FOUND" ) -> 2-s2.0-85092748091 | H43: =COUNTIF( G:G, G43 ) > 1 -> FALSE | I43: =COUNTIF( C:C, C43 ) > 1 -> FALSE
A44: jacovi_2021_formalizing_trust_ai | B44: Jacovi A.; Marasović A.; Miller T.; Goldberg Y. | C44: Formalizing trust in artificial intelligence: Prerequisites, causes and goals of human trust in AI | D44: Empirical | E44: Yes | F44: Yes | G44: =_xlfn.XLOOKUP( C44,RAW_DATA!B:B, RAW_DATA!Q:Q, "NOT FOUND" ) -> 2-s2.0-85102636939 | H44: =COUNTIF( G:G, G44 ) > 1 -> FALSE | I44: =COUNTIF( C:C, C44 ) > 1 -> FALSE
B45: Robinette P.; Li W.; Allen R.; Howard A.M.; Wagner A.R. | C45: Overtrust of robots in emergency evacuation scenarios | E45: No | F45: No | G45: =_xlfn.XLOOKUP( C45,RAW_DATA!B:B, RAW_DATA!Q:Q, "NOT FOUND" ) -> 2-s2.0-84964846793 | H45: =COUNTIF( G:G, G45 ) > 1 -> FALSE | I45: =COUNTIF( C:C, C45 ) > 1 -> FALSE
B46: Chi O.H.; Jia S.; Li Y.; Gursoy D. | C46: Developing a formative scale to measure consumers’ trust toward interaction with artificially intelligent (AI) social robots in service delivery | E46: No | F46: No | G46: =_xlfn.XLOOKUP( C46,RAW_DATA!B:B, RAW_DATA!Q:Q, "NOT FOUND" ) -> 2-s2.0-85099979829 | H46: =COUNTIF( G:G, G46 ) > 1 -> FALSE | I46: =COUNTIF( C:C, C46 ) > 1 -> FALSE
B47: Kaur D.; Uslu S.; Rittichier K.J.; Durresi A. | C47: Trustworthy Artificial Intelligence: A Review | E47: Yes | F47: No | G47: =_xlfn.XLOOKUP( C47,RAW_DATA!B:B, RAW_DATA!Q:Q, "NOT FOUND" ) -> 2-s2.0-85128190943 | H47: =COUNTIF( G:G, G47 ) > 1 -> FALSE | I47: =COUNTIF( C:C, C47 ) > 1 -> FALSE
B48: König M.; Neumayr L. | C48: Users’ resistance towards radical innovations: The case of the self-driving car | E48: Yes | F48: No | G48: =_xlfn.XLOOKUP( C48,RAW_DATA!B:B, RAW_DATA!Q:Q, "NOT FOUND" ) -> 2-s2.0-84995549556 | H48: =COUNTIF( G:G, G48 ) > 1 -> FALSE | I48: =COUNTIF( C:C, C48 ) > 1 -> FALSE
A49: chi_formative_scale | B49: Albahri A.S.; Duhaim A.M.; Fadhel M.A.; Alnoor A.; Baqer N.S.; Alzubaidi L.; Albahri O.S.; Alamoodi A.H.; Bai J.; Salhi A.; Santamaría J.; Ouyang C.; Gupta A.; Gu Y.; Deveci M. | C49: A systematic review of trustworthy and explainable artificial intelligence in healthcare: Assessment of quality, bias risk, and data fusion | D49: Empirical | E49: Yes | F49: Yes | G49: =_xlfn.XLOOKUP( C49,RAW_DATA!B:B, RAW_DATA!Q:Q, "NOT FOUND" ) -> 2-s2.0-85151265419 | H49: =COUNTIF( G:G, G49 ) > 1 -> FALSE | I49: =COUNTIF( C:C, C49 ) > 1 -> FALSE
B50: Laux J.; Wachter S.; Mittelstadt B. | C50: Trustworthy artificial intelligence and the European Union AI act: On the conflation of trustworthiness and acceptability of risk | D50: N/A | E50: Yes | F50: No | G50: =_xlfn.XLOOKUP( C50,RAW_DATA!B:B, RAW_DATA!Q:Q, "NOT FOUND" ) -> 2-s2.0-85147512970 | H50: =COUNTIF( G:G, G50 ) > 1 -> FALSE | I50: =COUNTIF( C:C, C50 ) > 1 -> FALSE
B51: Hancock P.A.; Nourbakhsh I.; Stewart J. | C51: On the future of transportation in an era of automated and autonomous vehicles | D51: N/A | E51: Yes | F51: No | G51: =_xlfn.XLOOKUP( C51,RAW_DATA!B:B, RAW_DATA!Q:Q, "NOT FOUND" ) -> 2-s2.0-85064355391 | H51: =COUNTIF( G:G, G51 ) > 1 -> FALSE | I51: =COUNTIF( C:C, C51 ) > 1 -> FALSE
B52: Ozmen Garibay O.; Winslow B.; Andolina S.; Antona M.; Bodenschatz A.; Coursaris C.; Falco G.; Fiore S.M.; Garibay I.; Grieman K.; Havens J.C.; Jirotka M.; Kacorri H.; Karwowski W.; Kider J.; Konstan J.; Koon S.; Lopez-Gonzalez M.; Maifeld-Carucci I.; McGregor S.; Salvendy G.; Shneiderman B.; Stephanidis C.; Strobel C.; Ten Holter C.; Xu W. | C52: Six Human-Centered Artificial Intelligence Grand Challenges | E52: No | F52: No | G52: =_xlfn.XLOOKUP( C52,RAW_DATA!B:B, RAW_DATA!Q:Q, "NOT FOUND" ) -> 2-s2.0-85145502740 | H52: =COUNTIF( G:G, G52 ) > 1 -> FALSE | I52: =COUNTIF( C:C, C52 ) > 1 -> FALSE
B53: Hermann E. | C53: Leveraging Artificial Intelligence in Marketing for Social Good—An Ethical Perspective | E53: No | F53: No | G53: =_xlfn.XLOOKUP( C53,RAW_DATA!B:B, RAW_DATA!Q:Q, "NOT FOUND" ) -> 2-s2.0-85106476454 | H53: =COUNTIF( G:G, G53 ) > 1 -> FALSE | I53: =COUNTIF( C:C, C53 ) > 1 -> FALSE
B54: Katzenbach C.; Ulbricht L. | C54: Algorithmic governance | E54: No | F54: No | G54: =_xlfn.XLOOKUP( C54,RAW_DATA!B:B, RAW_DATA!Q:Q, "NOT FOUND" ) -> 2-s2.0-85077848137 | H54: =COUNTIF( G:G, G54 ) > 1 -> FALSE | I54: =COUNTIF( C:C, C54 ) > 1 -> FALSE
B55: Omrani N.; Rivieccio G.; Fiore U.; Schiavone F.; Agreda S.G. | C55: To trust or not to trust? An assessment of trust in AI-based systems: Concerns, ethics and contexts | E55: No | F55: No | G55: =_xlfn.XLOOKUP( C55,RAW_DATA!B:B, RAW_DATA!Q:Q, "NOT FOUND" ) -> 2-s2.0-85130877872 | H55: =COUNTIF( G:G, G55 ) > 1 -> FALSE | I55: =COUNTIF( C:C, C55 ) > 1 -> FALSE
B56: Toreini E.; Aitken M.; Coopamootoo K.; Elliott K.; Zelaya C.G.; van Moorsel A. | C56: The relationship between trust in AI and trustworthy machine learning technologies | E56: No | F56: No | G56: =_xlfn.XLOOKUP( C56,RAW_DATA!B:B, RAW_DATA!Q:Q, "NOT FOUND" ) -> 2-s2.0-85079632241 | H56: =COUNTIF( G:G, G56 ) > 1 -> FALSE | I56: =COUNTIF( C:C, C56 ) > 1 -> FALSE
B57: Choung H.; David P.; Ross A. | C57: Trust in AI and Its Role in the Acceptance of AI Technologies | E57: No | F57: No | G57: =_xlfn.XLOOKUP( C57,RAW_DATA!B:B, RAW_DATA!Q:Q, "NOT FOUND" ) -> 2-s2.0-85129401047 | H57: =COUNTIF( G:G, G57 ) > 1 -> FALSE | I57: =COUNTIF( C:C, C57 ) > 1 -> FALSE
B58: Dixit V.V.; Chand S.; Nair D.J. | C58: Autonomous vehicles: Disengagements, accidents and reaction times | E58: No | F58: No | G58: =_xlfn.XLOOKUP( C58,RAW_DATA!B:B, RAW_DATA!Q:Q, "NOT FOUND" ) -> 2-s2.0-85006900493 | H58: =COUNTIF( G:G, G58 ) > 1 -> FALSE | I58: =COUNTIF( C:C, C58 ) > 1 -> FALSE
B59: Jing P.; Xu G.; Chen Y.; Shi Y.; Zhan F. | C59: The determinants behind the acceptance of autonomous vehicles: A systematic review | D59: N/A | E59: Yes | F59: No | G59: =_xlfn.XLOOKUP( C59,RAW_DATA!B:B, RAW_DATA!Q:Q, "NOT FOUND" ) -> 2-s2.0-85082878572 | H59: =COUNTIF( G:G, G59 ) > 1 -> FALSE | I59: =COUNTIF( C:C, C59 ) > 1 -> FALSE
B60: Zhang J.; Zhang Z.-M. | C60: Ethics and governance of trustworthy medical artificial intelligence | E60: Yes | F60: No | G60: =_xlfn.XLOOKUP( C60,RAW_DATA!B:B, RAW_DATA!Q:Q, "NOT FOUND" ) -> 2-s2.0-85146278182 | H60: =COUNTIF( G:G, G60 ) > 1 -> FALSE | I60: =COUNTIF( C:C, C60 ) > 1 -> FALSE
B61: Zirar A.; Ali S.I.; Islam N. | C61: Worker and workplace Artificial Intelligence (AI) coexistence: Emerging themes and research agenda | E61: No | F61: No | G61: =_xlfn.XLOOKUP( C61,RAW_DATA!B:B, RAW_DATA!Q:Q, "NOT FOUND" ) -> 2-s2.0-85150032477 | H61: =COUNTIF( G:G, G61 ) > 1 -> FALSE | I61: =COUNTIF( C:C, C61 ) > 1 -> FALSE
B62: Jarrahi M.H.; Newlands G.; Lee M.K.; Wolf C.T.; Kinder E.; Sutherland W. | C62: Algorithmic management in a work context | E62: No | F62: No | G62: =_xlfn.XLOOKUP( C62,RAW_DATA!B:B, RAW_DATA!Q:Q, "NOT FOUND" ) -> 2-s2.0-85109319306 | H62: =COUNTIF( G:G, G62 ) > 1 -> FALSE | I62: =COUNTIF( C:C, C62 ) > 1 -> FALSE
B63: Hasan R.; Shams R.; Rahman M. | C63: Consumer trust and perceived risk for voice-controlled artificial intelligence: The case of Siri | E63: Yes | F63: No | G63: =_xlfn.XLOOKUP( C63,RAW_DATA!B:B, RAW_DATA!Q:Q, "NOT FOUND" ) -> 2-s2.0-85098163651 | H63: =COUNTIF( G:G, G63 ) > 1 -> FALSE | I63: =COUNTIF( C:C, C63 ) > 1 -> FALSE
B64: Suresh H.; Guttag J. | C64: A Framework for Understanding Sources of Harm throughout the Machine Learning Life Cycle | E64: No | F64: No | G64: =_xlfn.XLOOKUP( C64,RAW_DATA!B:B, RAW_DATA!Q:Q, "NOT FOUND" ) -> 2-s2.0-85119301669 | H64: =COUNTIF( G:G, G64 ) > 1 -> FALSE | I64: =COUNTIF( C:C, C64 ) > 1 -> FALSE
A65: de_visser_longitudinal_trust | B65: de Visser E.J.; Peeters M.M.M.; Jung M.F.; Kohn S.; Shaw T.H.; Pak R.; Neerincx M.A. | C65: Towards a Theory of Longitudinal Trust Calibration in Human–Robot Teams | D65: Theoretical | E65: Yes | F65: Yes | G65: =_xlfn.XLOOKUP( C65,RAW_DATA!B:B, RAW_DATA!Q:Q, "NOT FOUND" ) -> 2-s2.0-85084924592 | H65: =COUNTIF( G:G, G65 ) > 1 -> FALSE | I65: =COUNTIF( C:C, C65 ) > 1 -> FALSE
B66: Park S. | C66: Multifaceted trust in tourism service robots | E66: No | F66: No | G66: =_xlfn.XLOOKUP( C66,RAW_DATA!B:B, RAW_DATA!Q:Q, "NOT FOUND" ) -> 2-s2.0-85080112789 | H66: =COUNTIF( G:G, G66 ) > 1 -> FALSE | I66: =COUNTIF( C:C, C66 ) > 1 -> FALSE
B67: Zhang Y.; Vera Liao Q.; Bellamy R.K.E. | C67: Efect of confidence and explanation on accuracy and trust calibration in AI-assisted decision making | E67: No | F67: No | G67: =_xlfn.XLOOKUP( C67,RAW_DATA!B:B, RAW_DATA!Q:Q, "NOT FOUND" ) -> 2-s2.0-85079608746 | H67: =COUNTIF( G:G, G67 ) > 1 -> FALSE | I67: =COUNTIF( C:C, C67 ) > 1 -> FALSE
B68: Ameen N.; Tarhini A.; Reppel A.; Anand A. | C68: Customer experiences in the age of artificial intelligence | E68: Yes | F68: No | G68: =_xlfn.XLOOKUP( C68,RAW_DATA!B:B, RAW_DATA!Q:Q, "NOT FOUND" ) -> 2-s2.0-85090737455 | H68: =COUNTIF( G:G, G68 ) > 1 -> FALSE | I68: =COUNTIF( C:C, C68 ) > 1 -> FALSE
B69: Siau K.; Wang W. | C69: Artificial intelligence (AI) Ethics: Ethics of AI and ethical AI | E69: No | F69: No | G69: =_xlfn.XLOOKUP( C69,RAW_DATA!B:B, RAW_DATA!Q:Q, "NOT FOUND" ) -> 2-s2.0-85097225749 | H69: =COUNTIF( G:G, G69 ) > 1 -> FALSE | I69: =COUNTIF( C:C, C69 ) > 1 -> FALSE
B70: Habbal A.; Ali M.K.; Abuzaraida M.A. | C70: Artificial Intelligence Trust, Risk and Security Management (AI TRiSM): Frameworks, applications, challenges and future research directions | E70: Yes | F70: No | G70: =_xlfn.XLOOKUP( C70,RAW_DATA!B:B, RAW_DATA!Q:Q, "NOT FOUND" ) -> 2-s2.0-85179498220 | H70: =COUNTIF( G:G, G70 ) > 1 -> FALSE | I70: =COUNTIF( C:C, C70 ) > 1 -> FALSE
B71: Vasconcelos H.; Jörke M.; Grunde-Mclaughlin M.; Gerstenberg T.; Bernstein M.S.; Krishna R. | C71: Explanations Can Reduce Overreliance on AI Systems During Decision-Making | E71: Yes | F71: No | G71: =_xlfn.XLOOKUP( C71,RAW_DATA!B:B, RAW_DATA!Q:Q, "NOT FOUND" ) -> 2-s2.0-85153706246 | H71: =COUNTIF( G:G, G71 ) > 1 -> FALSE | I71: =COUNTIF( C:C, C71 ) > 1 -> FALSE
A72: Buçinca_Proxy_tasks | B72: Buçinca Z.; Lin P.; Gajos K.Z.; Glassman E.L. | C72: Proxy tasks and subjective measures can be misleading in evaluating explainable AI systems | D72: Empirical | E72: Yes | F72: Yes | G72: =_xlfn.XLOOKUP( C72,RAW_DATA!B:B, RAW_DATA!Q:Q, "NOT FOUND" ) -> 2-s2.0-85082481569 | H72: =COUNTIF( G:G, G72 ) > 1 -> FALSE | I72: =COUNTIF( C:C, C72 ) > 1 -> FALSE
B73: Saeed W.; Omlin C. | C73: Explainable AI (XAI): A systematic meta-survey of current challenges and future opportunities | E73: No | F73: No | G73: =_xlfn.XLOOKUP( C73,RAW_DATA!B:B, RAW_DATA!Q:Q, "NOT FOUND" ) -> 2-s2.0-85146268490 | H73: =COUNTIF( G:G, G73 ) > 1 -> FALSE | I73: =COUNTIF( C:C, C73 ) > 1 -> FALSE
B74: Mariani M.M.; Perez-Vega R.; Wirtz J. | C74: AI in marketing, consumer research and psychology: A systematic literature review and research agenda | E74: Yes | F74: No | G74: =_xlfn.XLOOKUP( C74,RAW_DATA!B:B, RAW_DATA!Q:Q, "NOT FOUND" ) -> 2-s2.0-85120872880 | H74: =COUNTIF( G:G, G74 ) > 1 -> FALSE | I74: =COUNTIF( C:C, C74 ) > 1 -> FALSE
A75: habbal2024artificial | B75: Lee M.K. | C75: Understanding perception of algorithmic decisions: Fairness, trust, and emotion in response to algorithmic management | D75: Theoretical | E75: Yes | F75: Yes | G75: =_xlfn.XLOOKUP( C75,RAW_DATA!B:B, RAW_DATA!Q:Q, "NOT FOUND" ) -> 2-s2.0-85056605201 | H75: =COUNTIF( G:G, G75 ) > 1 -> FALSE | I75: =COUNTIF( C:C, C75 ) > 1 -> FALSE
B76: Gama F.; Magistretti S. | C76: Artificial intelligence in innovation management: A review of innovation capabilities and a taxonomy of AI applications | E76: Yes | F76: No | G76: =_xlfn.XLOOKUP( C76,RAW_DATA!B:B, RAW_DATA!Q:Q, "NOT FOUND" ) -> 2-s2.0-85172167777 | H76: =COUNTIF( G:G, G76 ) > 1 -> FALSE | I76: =COUNTIF( C:C, C76 ) > 1 -> FALSE
A77: choudhury_chat_gpt | B77: Choudhury A.; Shamszare H. | C77: Investigating the Impact of User Trust on the Adoption and Use of ChatGPT: Survey Analysis | D77: Empirical | E77: Yes | F77: Yes | G77: =_xlfn.XLOOKUP( C77,RAW_DATA!B:B, RAW_DATA!Q:Q, "NOT FOUND" ) -> 2-s2.0-85159924829 | H77: =COUNTIF( G:G, G77 ) > 1 -> FALSE | I77: =COUNTIF( C:C, C77 ) > 1 -> FALSE
A78: aoki_chatbot_experimental | B78: Aoki N. | C78: An experimental study of public trust in AI chatbots in the public sector | D78: Empirical | E78: Yes | F78: Yes | G78: =_xlfn.XLOOKUP( C78,RAW_DATA!B:B, RAW_DATA!Q:Q, "NOT FOUND" ) -> 2-s2.0-85089530712 | H78: =COUNTIF( G:G, G78 ) > 1 -> FALSE | I78: =COUNTIF( C:C, C78 ) > 1 -> FALSE
B79: Buçinca Z.; Malaya M.B.; Gajos K.Z. | C79: To Trust or to Think: Cognitive Forcing Functions Can Reduce Overreliance on AI in AI-assisted Decision-making | E79: No | F79: No | G79: =_xlfn.XLOOKUP( C79,RAW_DATA!B:B, RAW_DATA!Q:Q, "NOT FOUND" ) -> 2-s2.0-85115723507 | H79: =COUNTIF( G:G, G79 ) > 1 -> FALSE | I79: =COUNTIF( C:C, C79 ) > 1 -> FALSE
B80: Spinner T.; Schlegel U.; Schäfer H.; El-Assady M. | C80: ExplAIner: A Visual Analytics Framework for Interactive and Explainable Machine Learning | E80: No | F80: No | G80: =_xlfn.XLOOKUP( C80,RAW_DATA!B:B, RAW_DATA!Q:Q, "NOT FOUND" ) -> 2-s2.0-85075593782 | H80: =COUNTIF( G:G, G80 ) > 1 -> FALSE | I80: =COUNTIF( C:C, C80 ) > 1 -> FALSE
B81: Rudolph C.W.; Allan B.; Clark M.; Hertel G.; Hirschi A.; Kunze F.; Shockley K.; Shoss M.; Sonnentag S.; Zacher H. | C81: Pandemics: Implications for research and practice in industrial and organizational psychology | E81: No | F81: No | G81: =_xlfn.XLOOKUP( C81,RAW_DATA!B:B, RAW_DATA!Q:Q, "NOT FOUND" ) -> 2-s2.0-85106604957 | H81: =COUNTIF( G:G, G81 ) > 1 -> FALSE | I81: =COUNTIF( C:C, C81 ) > 1 -> FALSE
B82: Lai V.; Tan C. | C82: On human predictions with explanations and predictions of machine learning models: A case study on deception detection | E82: No | F82: No | G82: =_xlfn.XLOOKUP( C82,RAW_DATA!B:B, RAW_DATA!Q:Q, "NOT FOUND" ) -> 2-s2.0-85061781028 | H82: =COUNTIF( G:G, G82 ) > 1 -> FALSE | I82: =COUNTIF( C:C, C82 ) > 1 -> FALSE
B83: Schepman A.; Rodway P. | C83: Initial validation of the general attitudes towards Artificial Intelligence Scale | E83: Yes | F83: No | G83: =_xlfn.XLOOKUP( C83,RAW_DATA!B:B, RAW_DATA!Q:Q, "NOT FOUND" ) -> 2-s2.0-85096303826 | H83: =COUNTIF( G:G, G83 ) > 1 -> FALSE | I83: =COUNTIF( C:C, C83 ) > 1 -> FALSE
B84: de Visser E.J.; Pak R.; Shaw T.H. | C84: From ‘automation’ to ‘autonomy’: the importance of trust repair in human–machine interaction | E84: No | F84: No | G84: =_xlfn.XLOOKUP( C84,RAW_DATA!B:B, RAW_DATA!Q:Q, "NOT FOUND" ) -> 2-s2.0-85045104296 | H84: =COUNTIF( G:G, G84 ) > 1 -> FALSE | I84: =COUNTIF( C:C, C84 ) > 1 -> FALSE
A85: kaplan2021trust | B85: Kaplan A.D.; Kessler T.T.; Brill J.C.; Hancock P.A. | C85: Trust in Artificial Intelligence: Meta-Analytic Findings | D85: Empirical | E85: Yes | F85: Yes | G85: =_xlfn.XLOOKUP( C85,RAW_DATA!B:B, RAW_DATA!Q:Q, "NOT FOUND" ) -> 2-s2.0-85106720283 | H85: =COUNTIF( G:G, G85 ) > 1 -> FALSE | I85: =COUNTIF( C:C, C85 ) > 1 -> FALSE
B86: Kim N.J.; Kim M.K. | C86: Teacher’s Perceptions of Using an Artificial Intelligence-Based Educational Tool for Scientific Writing | E86: Yes | F86: No | G86: =_xlfn.XLOOKUP( C86,RAW_DATA!B:B, RAW_DATA!Q:Q, "NOT FOUND" ) -> 2-s2.0-85128424819 | H86: =COUNTIF( G:G, G86 ) > 1 -> FALSE | I86: =COUNTIF( C:C, C86 ) > 1 -> FALSE
B87: Körber M.; Baseler E.; Bengler K. | C87: Introduction matters: Manipulating trust in automation and reliance in automated driving | E87: No | F87: No | G87: =_xlfn.XLOOKUP( C87,RAW_DATA!B:B, RAW_DATA!Q:Q, "NOT FOUND" ) -> 2-s2.0-85029816073 | H87: =COUNTIF( G:G, G87 ) > 1 -> FALSE | I87: =COUNTIF( C:C, C87 ) > 1 -> FALSE
B88: Celik I. | C88: Towards Intelligent-TPACK: An empirical study on teachers’ professional knowledge to ethically integrate artificial intelligence (AI)-based tools into education | E88: No | F88: No | G88: =_xlfn.XLOOKUP( C88,RAW_DATA!B:B, RAW_DATA!Q:Q, "NOT FOUND" ) -> 2-s2.0-85137060930 | H88: =COUNTIF( G:G, G88 ) > 1 -> FALSE | I88: =COUNTIF( C:C, C88 ) > 1 -> FALSE
B89: Lebovitz S.; Lifshitz-Assaf H.; Levina N. | C89: To Engage or Not to Engage with AI for Critical Judgments: How Professionals Deal with Opacity When Using AI for Medical Diagnosis | E89: No | F89: No | G89: =_xlfn.XLOOKUP( C89,RAW_DATA!B:B, RAW_DATA!Q:Q, "NOT FOUND" ) -> 2-s2.0-85125569707 | H89: =COUNTIF( G:G, G89 ) > 1 -> FALSE | I89: =COUNTIF( C:C, C89 ) > 1 -> FALSE
B90: Jiang Z.; Araki J.; Ding H.; Neubig G. | C90: How can we know when language models know? On the calibration of language models for question answering | E90: Yes | F90: No | G90: =_xlfn.XLOOKUP( C90,RAW_DATA!B:B, RAW_DATA!Q:Q, "NOT FOUND" ) -> 2-s2.0-85119501865 | H90: =COUNTIF( G:G, G90 ) > 1 -> FALSE | I90: =COUNTIF( C:C, C90 ) > 1 -> FALSE
B91: Makarius E.E.; Mukherjee D.; Fox J.D.; Fox A.K. | C91: Rising with the machines: A sociotechnical framework for bringing artificial intelligence into the organization | E91: Yes | F91: No | G91: =_xlfn.XLOOKUP( C91,RAW_DATA!B:B, RAW_DATA!Q:Q, "NOT FOUND" ) -> 2-s2.0-85089816705 | H91: =COUNTIF( G:G, G91 ) > 1 -> FALSE | I91: =COUNTIF( C:C, C91 ) > 1 -> FALSE
A92: larson_LeadingTeamsDigitalAge | B92: Larson L.; DeChurch L.A. | C92: Leading teams in the digital age: Four perspectives on technology and what they mean for leading teams | D92: Theoretical | E92: Yes | F92: Yes | G92: =_xlfn.XLOOKUP( C92,RAW_DATA!B:B, RAW_DATA!Q:Q, "NOT FOUND" ) -> 2-s2.0-85077758620 | H92: =COUNTIF( G:G, G92 ) > 1 -> FALSE | I92: =COUNTIF( C:C, C92 ) > 1 -> FALSE
B93: Kelly S.; Kaye S.-A.; Oviedo-Trespalacios O. | C93: What factors contribute to the acceptance of artificial intelligence? A systematic review | E93: No | F93: No | G93: =_xlfn.XLOOKUP( C93,RAW_DATA!B:B, RAW_DATA!Q:Q, "NOT FOUND" ) -> 2-s2.0-85144829011 | H93: =COUNTIF( G:G, G93 ) > 1 -> FALSE | I93: =COUNTIF( C:C, C93 ) > 1 -> FALSE
A94: Wang_yin_2021 | B94: Wang X.; Yin M. | C94: Are Explanations Helpful? A Comparative Study of the Effects of Explanations in AI-Assisted Decision-Making | D94: empirical | E94: Yes | F94: Yes | G94: =_xlfn.XLOOKUP( C94,RAW_DATA!B:B, RAW_DATA!Q:Q, "NOT FOUND" ) -> 2-s2.0-85104503567 | H94: =COUNTIF( G:G, G94 ) > 1 -> FALSE | I94: =COUNTIF( C:C, C94 ) > 1 -> FALSE
B95: Bansal G.; Nushi B.; Kamar E.; Weld D.S.; Lasecki W.S.; Horvitz E. | C95: Updates in human-ai teams: Understanding and addressing the performance/compatibility tradeoff | E95: No | F95: No | G95: =_xlfn.XLOOKUP( C95,RAW_DATA!B:B, RAW_DATA!Q:Q, "NOT FOUND" ) -> 2-s2.0-85079599165 | H95: =COUNTIF( G:G, G95 ) > 1 -> FALSE | I95: =COUNTIF( C:C, C95 ) > 1 -> FALSE
B96: Rheu M.; Shin J.Y.; Peng W.; Huh-Yoo J. | C96: Systematic Review: Trust-Building Factors and Implications for Conversational Agent Design | E96: No | F96: No | G96: =_xlfn.XLOOKUP( C96,RAW_DATA!B:B, RAW_DATA!Q:Q, "NOT FOUND" ) -> 2-s2.0-85090125043 | H96: =COUNTIF( G:G, G96 ) > 1 -> FALSE | I96: =COUNTIF( C:C, C96 ) > 1 -> FALSE
B97: Vaccaro M.; Almaatouq A.; Malone T. | C97: When combinations of humans and AI are useful: A systematic review and meta-analysis | E97: No | F97: No | G97: =_xlfn.XLOOKUP( C97,RAW_DATA!B:B, RAW_DATA!Q:Q, "NOT FOUND" ) -> 2-s2.0-85207410244 | H97: =COUNTIF( G:G, G97 ) > 1 -> FALSE | I97: =COUNTIF( C:C, C97 ) > 1 -> FALSE
B98: Chiu T.K.F.; Xia Q.; Zhou X.; Chai C.S.; Cheng M. | C98: Systematic literature review on opportunities, challenges, and future research recommendations of artificial intelligence in education | E98: Yes | F98: No | G98: =_xlfn.XLOOKUP( C98,RAW_DATA!B:B, RAW_DATA!Q:Q, "NOT FOUND" ) -> 2-s2.0-85144966908 | H98: =COUNTIF( G:G, G98 ) > 1 -> FALSE | I98: =COUNTIF( C:C, C98 ) > 1 -> FALSE
B99: Sacha D.; Senaratne H.; Kwon B.C.; Ellis G.; Keim D.A. | C99: The Role of Uncertainty, Awareness, and Trust in Visual Analytics | E99: No | F99: No | G99: =_xlfn.XLOOKUP( C99,RAW_DATA!B:B, RAW_DATA!Q:Q, "NOT FOUND" ) -> 2-s2.0-84946595461 | H99: =COUNTIF( G:G, G99 ) > 1 -> FALSE | I99: =COUNTIF( C:C, C99 ) > 1 -> FALSE
A100: What_factors_contribute_to_the_acceptance_of_artificial_intelligence | B100: Choi S.; Jang Y.; Kim H. | C100: Influence of Pedagogical Beliefs and Perceived Trust on Teachers’ Acceptance of Educational Artificial Intelligence Tools | D100: Empirical | E100: Yes | F100: Yes | G100: =_xlfn.XLOOKUP( C100,RAW_DATA!B:B, RAW_DATA!Q:Q, "NOT FOUND" ) -> 2-s2.0-85129236620 | H100: =COUNTIF( G:G, G100 ) > 1 -> FALSE | I100: =COUNTIF( C:C, C100 ) > 1 -> FALSE
...

Sheet Codes
B1: Reference | C1: Factor | D1: Layer | E1: Subdivision | F1: Interpretation | G1: [Autofilled] Valid Reference?
B2: jacovi_2021_formalizing_trust_ai | C2: Warranted Trust (Calibration) | D2: Adaptive Trust Dynamics | E2: Calibration | F2: Alignment between perceived and actual trustworthiness | G2: =IF( COUNTIF( Papers!A:A, B2 ) > 0, "OK", "KO" ) -> OK
B3: carsten_hmi_automated_cars | C3: Calibration | D3: Adaptive Trust Dynamics | E3: Calibration | F3: Understanding system capabilities for correct reliance | G3: =IF( COUNTIF( Papers!A:A, B3 ) > 0, "OK", "KO" ) -> OK
B4: de_visser_longitudinal_trust | C4: Feedback loop | D4: Adaptive Trust Dynamics | E4: Feedback | F4: Outcomes influence future trust | G4: =IF( COUNTIF( Papers!A:A, B4 ) > 0, "OK", "KO" ) -> OK
B5: wang2019artificial | C5: Continuous learning | D5: Adaptive Trust Dynamics | E5: Learning | F5: System adapts over time | G5: =IF( COUNTIF( Papers!A:A, B5 ) > 0, "OK", "KO" ) -> OK
B6: wang2019artificial | C6: Evolution | D6: Adaptive Trust Dynamics | E6: Learning | F6: System evolves and improves performance | G6: =IF( COUNTIF( Papers!A:A, B6 ) > 0, "OK", "KO" ) -> OK
B7: vereschak2021evaluate | C7: Static vs. Dynamic Trust | D7: Adaptive Trust Dynamics | E7: Temporal Evolution | F7: Trust changes over time through interaction | G7: =IF( COUNTIF( Papers!A:A, B7 ) > 0, "OK", "KO" ) -> OK
B8: schepman_general_attitude | C8: Trust Transfer | D8: Adaptive Trust Dynamics | E8: Transfer Mechanism | F8: Process by which trust in humans extends to AI systems they design | G8: =IF( COUNTIF( Papers!A:A, B8 ) > 0, "OK", "KO" ) -> OK
B9: choudhury_chat_gpt | C9: Mediation (Trust → Intent → Use) | D9: Adaptive Trust Dynamics | E9: Temporal Evolution | F9: Process where intent to use mediates the effect of trust on actual usage behavior | G9: =IF( COUNTIF( Papers!A:A, B9 ) > 0, "OK", "KO" ) -> OK
B10: glickson_2020_review_of_empirical_research | C10: Task Characteristics | D10: Context | E10: Task | F10: Trust varies depending on task type | G10: =IF( COUNTIF( Papers!A:A, B10 ) > 0, "OK", "KO" ) -> OK
B11: jacovi_2021_formalizing_trust_ai | C11: Vulnerability / Risk | D11: Context | E11: Risk | F11: Trust involves exposure to potential failure | G11: =IF( COUNTIF( Papers!A:A, B11 ) > 0, "OK", "KO" ) -> OK
B12: de_visser_longitudinal_trust | C12: Vulnerability / Risk | D12: Context | E12: Risk | F12: Trust involves exposure to potential failure | G12: =IF( COUNTIF( Papers!A:A, B12 ) > 0, "OK", "KO" ) -> OK
B13: young_patient_systematic_review | C13: Human in the loop | D13: Context | E13: Environment | F13: Presence of human oversight | G13: =IF( COUNTIF( Papers!A:A, B13 ) > 0, "OK", "KO" ) -> OK
... B80: Tong_artificial_intelligence_feedback | C80: Perceived Empathy | D80: Subjective Perception | E80: Social Perception | F80: Perceived ability of the AI to understand human emotional and contextual nuances. | G80: =IF( COUNTIF( Papers!A:A, B80 ) > 0, "OK", "KO" ) -> OK

Sheet Statistics
B4: Total Papers | D4: =COUNTA( Papers!C:C ) - 1 -> 599
D6: Count | E6: Perc
B7: TITLE | C7: PASS | D7: =COUNTIF( Papers!E:E, "Yes" ) -> 266 | E7: =D7/$D$4 -> 0.44407346 | G7: Empirical
C8: FAIL | D8: =COUNTIF( Papers!E:E, "No" ) -> 333 | E8: =D8/$D$4 -> 0.55592654 | G8: Theoretical
C9: Checksum | D9: =IF(SUM(D7:D8)=$D$4,"OK","KO") -> OK | G9: Practical
B10: ABSTRACT (Absolute) | C10: PASS | D10: =COUNTIF( Papers!F:F, "Yes" ) -> 47 | E10: =D10/$D$4 -> 0.078464107
C11: FAIL | D11: =COUNTIF( Papers!F:F, "No" ) -> 552 | E11: =D11/$D$4 -> 0.92153589
C12: Checksum | D12: =IF(SUM(D10:D11)=$D$4,"OK","KO") -> OK
B13: ABSTRACT (Relative) | C13: PASS | D13: =COUNTIFS( Papers!E:E, "Yes", Papers!F:F, "Yes" ) -> 47 | E13: =D13/$D$7 -> 0.17669173
C14: FAIL | D14: =COUNTIFS( Papers!E:E, "Yes", Papers!F:F, "No" ) -> 219 | E14: =D14/$D$7 -> 0.82330827
C15: Checksum | D15: =IF(SUM(D13:D14)=$D$7,"OK","KO") -> OK
C18: Total selected Empirical | D18: =COUNTIFS( Papers!F:F, "Yes", Papers!D:D, G7 ) -> 24 | E18: =D18/$D$10 -> 0.5106383
C19: Total selected Theoretical | D19: =COUNTIFS( Papers!F:F, "Yes", Papers!D:D, G8 ) -> 22 | E19: =D19/$D$10 -> 0.46808511
C20: Total selected Practical | D20: =COUNTIFS( Papers!F:F, "Yes", Papers!D:D, G9 ) -> 1 | E20: =D20/$D$10 -> 0.021276596
C21: Checksum | D21: =IF(SUM(D18:D20)=D10,"OK","KO") -> OK

Sheet Query
B2: "trust in artificial intelligence" OR "trust in automation" OR "trust calibration" AND ( LIMIT-TO ( DOCTYPE , "ar" ) OR LIMIT-TO ( DOCTYPE , "cp" ) OR LIMIT-TO ( DOCTYPE , "re" ) OR LIMIT-TO ( DOCTYPE , "ch" ) OR LIMIT-TO ( DOCTYPE , "cr" ) OR LIMIT-TO ( DOCTYPE , "sh" ) ) AND ( LIMIT-TO ( LANGUAGE , "English" ) ) AND PUBYEAR > 2015 AND PUBYEAR < 2026
